Workbook

Sheet Read me
A1: COLOMBIA | NATURAL GAS IMPORTS
A2: Research snapshot: 27 October 2026. Actual customs observations, selected bulletin extracts and forward scenarios are kept separate.
A5: LNG imports: 2025, CIF | D5: Annual LNG coverage | G5: National monthly customs
A6: ='Annual imports'!E15 -> 779.20366 | D6: 2017-2025 | G6: NOT LOADED
A9: Coverage limitation: the public annual tables were retrieved, but DANE ZIP downloads and the BMC terminal-level export were not obtained. This workbook does not claim a complete monthly customs scrape.
A12: START WITH THE CHARTS
A13: Annual LNG dollar values, partner composition and the BMC supply-demand scenario are already charted.
A15: USE THE CLEAN TABLES
A16: Annual imports is the chart-ready national table. Annual raw and Partners retain source values, units, links and flags.
A18: KEEP THE BMC SCENARIO SEPARATE
A19: 14 exact visible rows from October 2026 to November 2027. Only domestic supply inputs, not total supply, can be used to infer residual import needs.
A21: ADD THE MONTHLY ARCHIVES
A22: The bundle includes load_dane_monthly.py. Supply DANE ZIPs to produce monthly FOB, CIF, net kg and country detail, plus CSV, SQLite and Excel outputs.
A24: AUDIT BEFORE INTERPRETING
A25: Review the 2025 country-label reconciliation, missing quantities, CIF versus FOB and the 2025 country-code change.
A28: Source attribution: World Bank WITS / UN Comtrade; DIAN-DANE; BMC screenshot supplied by the user. Fuente: Departamento Administrativo Nacional de Estadistica: www.dane.gov.co

Sheet Charts
A1: CHARTS | VERIFIED SERIES
A2: Editable Excel charts. Annual customs values are CIF. BMC lines are a forward supply-demand scenario, not imports.
A5: National customs series: only full calendar years are compared. Missing reported quantities are not filled.
A25: Partner chart: the 2025 WITS label Tanzania is reconciled to Trinidad and Tobago using DANE. The unaltered source label is retained in Partners.
A45: Forward scenario, not actual imports. Exact values come from the 14 rows visible in the supplied screenshot; no terminal-level bar values were inferred.
A66: Year | B66: United States | C66: Trinidad and Tobago | D66: United Kingdom | E66: Other reported partners
A67: 2017 | B67: =SUMIFS(Partners!$F$7:$F$43,Partners!$A$7:$A$43,A67,Partners!$B$7:$B$43,"271111",Partners!$D$7:$D$43,B$66)/Settings!$B$8 -> 0 | C67: =SUMIFS(Partners!$F$7:$F$43,Partners!$A$7:$A$43,A67,Partners!$B$7:$B$43,"271111",Partners!$D$7:$D$43,C$66)/Settings!$B$8 -> 0 | D67: =SUMIFS(Partners!$F$7:$F$43,Partners!$A$7:$A$43,A67,Partners!$B$7:$B$43,"271111",Partners!$D$7:$D$43,D$66)/Settings!$B$8 -> 0 | E67: =SUMIFS(Partners!$F$7:$F$43,Partners!$A$7:$A$43,A67,Partners!$B$7:$B$43,"271111")/Settings!$B$8-SUM(B67:D67) -> 11.92593
A68: 2018 | B68: =SUMIFS(Partners!$F$7:$F$43,Partners!$A$7:$A$43,A68,Partners!$B$7:$B$43,"271111",Partners!$D$7:$D$43,B$66)/Settings!$B$8 -> 39.55393 | C68: =SUMIFS(Partners!$F$7:$F$43,Partners!$A$7:$A$43,A68,Partners!$B$7:$B$43,"271111",Partners!$D$7:$D$43,C$66)/Settings!$B$8 -> 36.71102 | D68: =SUMIFS(Partners!$F$7:$F$43,Partners!$A$7:$A$43,A68,Partners!$B$7:$B$43,"271111",Partners!$D$7:$D$43,D$66)/Settings!$B$8 -> 32.60278 | E68: =SUMIFS(Partners!$F$7:$F$43,Partners!$A$7:$A$43,A68,Partners!$B$7:$B$43,"271111")/Settings!$B$8-SUM(B68:D68) -> 14.87964
A69: 2019 | B69: =SUMIFS(Partners!$F$7:$F$43,Partners!$A$7:$A$43,A69,Partners!$B$7:$B$43,"271111",Partners!$D$7:$D$43,B$66)/Settings!$B$8 -> 21.90239 | C69: =SUMIFS(Partners!$F$7:$F$43,Partners!$A$7:$A$43,A69,Partners!$B$7:$B$43,"271111",Partners!$D$7:$D$43,C$66)/Settings!$B$8 -> 7.83293 | D69: =SUMIFS(Partners!$F$7:$F$43,Partners!$A$7:$A$43,A69,Partners!$B$7:$B$43,"271111",Partners!$D$7:$D$43,D$66)/Settings!$B$8 -> 0 | E69: =SUMIFS(Partners!$F$7:$F$43,Partners!$A$7:$A$43,A69,Partners!$B$7:$B$43,"271111")/Settings!$B$8-SUM(B69:D69) -> 27.30873
A70: 2020 | B70: =SUMIFS(Partners!$F$7:$F$43,Partners!$A$7:$A$43,A70,Partners!$B$7:$B$43,"271111",Partners!$D$7:$D$43,B$66)/Settings!$B$8 -> 2.97281 | C70: =SUMIFS(Partners!$F$7:$F$43,Partners!$A$7:$A$43,A70,Partners!$B$7:$B$43,"271111",Partners!$D$7:$D$43,C$66)/Settings!$B$8 -> 13.41035 | D70: =SUMIFS(Partners!$F$7:$F$43,Partners!$A$7:$A$43,A70,Partners!$B$7:$B$43,"271111",Partners!$D$7:$D$43,D$66)/Settings!$B$8 -> 20.3398 | E70: =SUMIFS(Partners!$F$7:$F$43,Partners!$A$7:$A$43,A70,Partners!$B$7:$B$43,"271111")/Settings!$B$8-SUM(B70:D70) -> 23.18736
A71: 2021 | B71: =SUMIFS(Partners!$F$7:$F$43,Partners!$A$7:$A$43,A71,Partners!$B$7:$B$43,"271111",Partners!$D$7:$D$43,B$66)/Settings!$B$8 -> 14.51052 | C71: =SUMIFS(Partners!$F$7:$F$43,Partners!$A$7:$A$43,A71,Partners!$B$7:$B$43,"271111",Partners!$D$7:$D$43,C$66)/Settings!$B$8 -> 0 | D71: =SUMIFS(Partners!$F$7:$F$43,Partners!$A$7:$A$43,A71,Partners!$B$7:$B$43,"271111",Partners!$D$7:$D$43,D$66)/Settings!$B$8 -> 13.42246 | E71: =SUMIFS(Partners!$F$7:$F$43,Partners!$A$7:$A$43,A71,Partners!$B$7:$B$43,"271111")/Settings!$B$8-SUM(B71:D71) -> 0.00851
A72: 2022 | B72: =SUMIFS(Partners!$F$7:$F$43,Partners!$A$7:$A$43,A72,Partners!$B$7:$B$43,"271111",Partners!$D$7:$D$43,B$66)/Settings!$B$8 -> 87.55064 | C72: =SUMIFS(Partners!$F$7:$F$43,Partners!$A$7:$A$43,A72,Partners!$B$7:$B$43,"271111",Partners!$D$7:$D$43,C$66)/Settings!$B$8 -> 0 | D72: =SUMIFS(Partners!$F$7:$F$43,Partners!$A$7:$A$43,A72,Partners!$B$7:$B$43,"271111",Partners!$D$7:$D$43,D$66)/Settings!$B$8 -> 0 | E72: =SUMIFS(Partners!$F$7:$F$43,Partners!$A$7:$A$43,A72,Partners!$B$7:$B$43,"271111")/Settings!$B$8-SUM(B72:D72) -> 0
A73: 2023 | B73: =SUMIFS(Partners!$F$7:$F$43,Partners!$A$7:$A$43,A73,Partners!$B$7:$B$43,"271111",Partners!$D$7:$D$43,B$66)/Settings!$B$8 -> 410.85209 | C73: =SUMIFS(Partners!$F$7:$F$43,Partners!$A$7:$A$43,A73,Partners!$B$7:$B$43,"271111",Partners!$D$7:$D$43,C$66)/Settings!$B$8 -> 30.60301 | D73: =SUMIFS(Partners!$F$7:$F$43,Partners!$A$7:$A$43,A73,Partners!$B$7:$B$43,"271111",Partners!$D$7:$D$43,D$66)/Settings!$B$8 -> 0.00087 | E73: =SUMIFS(Partners!$F$7:$F$43,Partners!$A$7:$A$43,A73,Partners!$B$7:$B$43,"271111")/Settings!$B$8-SUM(B73:D73) -> 0
A74: 2024 | B74: =SUMIFS(Partners!$F$7:$F$43,Partners!$A$7:$A$43,A74,Partners!$B$7:$B$43,"271111",Partners!$D$7:$D$43,B$66)/Settings!$B$8 -> 771.97825 | C74: =SUMIFS(Partners!$F$7:$F$43,Partners!$A$7:$A$43,A74,Partners!$B$7:$B$43,"271111",Partners!$D$7:$D$43,C$66)/Settings!$B$8 -> 134.54294 | D74: =SUMIFS(Partners!$F$7:$F$43,Partners!$A$7:$A$43,A74,Partners!$B$7:$B$43,"271111",Partners!$D$7:$D$43,D$66)/Settings!$B$8 -> 38.92535 | E74: =SUMIFS(Partners!$F$7:$F$43,Partners!$A$7:$A$43,A74,Partners!$B$7:$B$43,"271111")/Settings!$B$8-SUM(B74:D74) -> 1.1368684e-13
A75: 2025 | B75: =SUMIFS(Partners!$F$7:$F$43,Partners!$A$7:$A$43,A75,Partners!$B$7:$B$43,"271111",Partners!$D$7:$D$43,B$66)/Settings!$B$8 -> 388.39081 | C75: =SUMIFS(Partners!$F$7:$F$43,Partners!$A$7:$A$43,A75,Partners!$B$7:$B$43,"271111",Partners!$D$7:$D$43,C$66)/Settings!$B$8 -> 390.80822 | D75: =SUMIFS(Partners!$F$7:$F$43,Partners!$A$7:$A$43,A75,Partners!$B$7:$B$43,"271111",Partners!$D$7:$D$43,D$66)/Settings!$B$8 -> 0.00463 | E75: =SUMIFS(Partners!$F$7:$F$43,Partners!$A$7:$A$43,A75,Partners!$B$7:$B$43,"271111")/Settings!$B$8-SUM(B75:D75) -> 0

Sheet Annual imports
A1: ANNUAL IMPORTS | CHART-READY
A2: LNG: 2017-2025. Gaseous natural gas: 2021-2025 only. Blank values mean unavailable in this extraction, not zero. World totals are not added to partner rows.
A6: Year | B6: LNG CIF (US$) | C6: Gaseous gas CIF (US$) | D6: Total natural gas CIF (US$) | E6: LNG CIF (US$ million) | F6: LNG reported quantity (tonnes) | G6: LNG CIF unit value (US$/tonne) | H6: LNG value YoY (%) | I6: Quantity status | J6: LNG source URL | K6: Gaseous-gas source URL
A7: 2017 | B7: ='Annual raw'!F7 -> 11925930 | D7: =IF(COUNT(B7:C7)=2,SUM(B7:C7),"") | E7: =B7/Settings!$B$8 -> 11.92593 | F7: =IF(ISNUMBER('Annual raw'!E7),'Annual raw'!E7/Settings!$B$9,"") -> 38942.6 | G7: =IF(AND(ISNUMBER(F7),F7>0),B7/F7,"") -> 306.2438 | I7: Reported | J7: https://wits.worldbank.org/trade/comtrade/en/country/COL/year/2017/tradeflow/Imports/partner/ALL/product/271111
A8: 2018 | B8: ='Annual raw'!F8 -> 123747360 | D8: =IF(COUNT(B8:C8)=2,SUM(B8:C8),"") | E8: =B8/Settings!$B$8 -> 123.74736 | F8: =IF(ISNUMBER('Annual raw'!E8),'Annual raw'!E8/Settings!$B$9,"") -> 239638 | G8: =IF(AND(ISNUMBER(F8),F8>0),B8/F8,"") -> 516.39289 | H8: =IFERROR(B8/B7-1,"") -> 9.3763279 | I8: Reported | J8: https://wits.worldbank.org/trade/comtrade/en/country/COL/year/2018/tradeflow/Imports/partner/ALL/product/271111
A9: 2019 | B9: ='Annual raw'!F9 -> 57044060 | D9: =IF(COUNT(B9:C9)=2,SUM(B9:C9),"") | E9: =B9/Settings!$B$8 -> 57.04406 | F9: =IF(ISNUMBER('Annual raw'!E9),'Annual raw'!E9/Settings!$B$9,"") | G9: =IF(AND(ISNUMBER(F9),F9>0),B9/F9,"") | H9: =IFERROR(B9/B8-1,"") -> -0.53902806 | I9: Missing in WITS; not zero | J9: https://wits.worldbank.org/trade/comtrade/en/country/COL/year/2019/tradeflow/Imports/partner/ALL/product/271111
A10: 2020 | B10: ='Annual raw'!F10 -> 59910330 | D10: =IF(COUNT(B10:C10)=2,SUM(B10:C10),"") | E10: =B10/Settings!$B$8 -> 59.91033 | F10: =IF(ISNUMBER('Annual raw'!E10),'Annual raw'!E10/Settings!$B$9,"") -> 296302 | G10: =IF(AND(ISNUMBER(F10),F10>0),B10/F10,"") -> 202.19347 | H10: =IFERROR(B10/B9-1,"") -> 0.050246599 | I10: Reported | J10: https://wits.worldbank.org/trade/comtrade/en/country/COL/year/2020/tradeflow/Imports/partner/ALL/product/271111
A11: 2021 | B11: ='Annual raw'!F11 -> 27941490 | C11: ='Annual raw'!F12 -> 43160 | D11: =IF(COUNT(B11:C11)=2,SUM(B11:C11),"") -> 27984650 | E11: =B11/Settings!$B$8 -> 27.94149 | F11: =IF(ISNUMBER('Annual raw'!E11),'Annual raw'!E11/Settings!$B$9,"") -> 44406 | G11: =IF(AND(ISNUMBER(F11),F11>0),B11/F11,"") -> 629.22781 | H11: =IFERROR(B11/B10-1,"") -> -0.53361148 | I11: Reported | J11: https://wits.worldbank.org/trade/comtrade/en/country/COL/year/2021/tradeflow/Imports/partner/ALL/product/271111 | K11: https://wits.worldbank.org/trade/comtrade/en/country/COL/year/2021/tradeflow/Imports/partner/ALL/product/271121
A12: 2022 | B12: ='Annual raw'!F13 -> 87550640 | C12: ='Annual raw'!F14 -> 84120 | D12: =IF(COUNT(B12:C12)=2,SUM(B12:C12),"") -> 87634760 | E12: =B12/Settings!$B$8 -> 87.55064 | F12: =IF(ISNUMBER('Annual raw'!E13),'Annual raw'!E13/Settings!$B$9,"") -> 60181 | G12: =IF(AND(ISNUMBER(F12),F12>0),B12/F12,"") -> 1454.7887 | H12: =IFERROR(B12/B11-1,"") -> 2.1333562 | I12: Reported | J12: https://wits.worldbank.org/trade/comtrade/en/country/COL/year/2022/tradeflow/Imports/partner/ALL/product/271111 | K12: https://wits.worldbank.org/trade/comtrade/en/country/COL/year/2022/tradeflow/Imports/partner/ALL/product/271121
A13: 2023 | B13: ='Annual raw'!F15 -> 441455970 | C13: ='Annual raw'!F16 -> 4930 | D13: =IF(COUNT(B13:C13)=2,SUM(B13:C13),"") -> 441460900 | E13: =B13/Settings!$B$8 -> 441.45597 | F13: =IF(ISNUMBER('Annual raw'!E15),'Annual raw'!E15/Settings!$B$9,"") | G13: =IF(AND(ISNUMBER(F13),F13>0),B13/F13,"") | H13: =IFERROR(B13/B12-1,"") -> 4.0422929 | I13: Missing in WITS; not zero | J13: https://wits.worldbank.org/trade/comtrade/en/country/COL/year/2023/tradeflow/Imports/partner/ALL/product/271111 | K13: https://wits.worldbank.org/trade/comtrade/en/country/COL/year/2023/tradeflow/Imports/partner/ALL/product/271121
A14: 2024 | B14: ='Annual raw'!F17 -> 945446540 | C14: ='Annual raw'!F18 -> 31740 | D14: =IF(COUNT(B14:C14)=2,SUM(B14:C14),"") -> 945478280 | E14: =B14/Settings!$B$8 -> 945.44654 | F14: =IF(ISNUMBER('Annual raw'!E17),'Annual raw'!E17/Settings!$B$9,"") -> 1625300 | G14: =IF(AND(ISNUMBER(F14),F14>0),B14/F14,"") -> 581.70586 | H14: =IFERROR(B14/B13-1,"") -> 1.1416554 | I14: Reported | J14: https://wits.worldbank.org/trade/comtrade/en/country/COL/year/2024/tradeflow/Imports/partner/ALL/product/271111 | K14: https://wits.worldbank.org/trade/comtrade/en/country/COL/year/2024/tradeflow/Imports/partner/ALL/product/271121
A15: 2025 | B15: ='Annual raw'!F19 -> 779203660 | C15: ='Annual raw'!F20 -> 27570 | D15: =IF(COUNT(B15:C15)=2,SUM(B15:C15),"") -> 779231230 | E15: =B15/Settings!$B$8 -> 779.20366 | F15: =IF(ISNUMBER('Annual raw'!E19),'Annual raw'!E19/Settings!$B$9,"") | G15: =IF(AND(ISNUMBER(F15),F15>0),B15/F15,"") | H15: =IFERROR(B15/B14-1,"") -> -0.1758353 | I15: Missing in WITS; not zero | J15: https://wits.worldbank.org/trade/comtrade/en/country/COL/year/2025/tradeflow/Imports/partner/ALL/product/271111 | K15: https://wits.worldbank.org/trade/comtrade/en/country/COL/year/2025/tradeflow/Imports/partner/ALL/product/271121
A18: CIF is not FOB. The annual series alone cannot give an exact contribution to the FOB merchandise-trade balance. Unit values are customs ratios, not LNG spot prices.

Sheet Annual raw
A1: ANNUAL RAW | PUBLISHED WORLD TOTALS
A2: Source values are displayed in US$ thousands on WITS. Converted dollars are formulas. Quantity is the WITS reported quantity field in kg; missing weights stay blank.
A6: Year | B6: HS6 | C6: Product | D6: Source value (US$ thousands) | E6: Reported quantity (kg) | F6: CIF value (US$) | G6: Quantity status | H6: Source URL | I6: Accessed
A7: 2017 | B7: 271111 | C7: LNG | D7: 11925.93 | E7: 38942600 | F7: =D7*Settings!$B$7 -> 11925930 | G7: reported | H7: https://wits.worldbank.org/trade/comtrade/en/country/COL/year/2017/tradeflow/Imports/partner/ALL/product/271111 | I7: 2026-10-27
A8: 2018 | B8: 271111 | C8: LNG | D8: 123747.36 | E8: 239638000 | F8: =D8*Settings!$B$7 -> 123747360 | G8: reported | H8: https://wits.worldbank.org/trade/comtrade/en/country/COL/year/2018/tradeflow/Imports/partner/ALL/product/271111 | I8: 2026-10-27
A9: 2019 | B9: 271111 | C9: LNG | D9: 57044.06 | F9: =D9*Settings!$B$7 -> 57044060 | G9: missing_not_zero | H9: https://wits.worldbank.org/trade/comtrade/en/country/COL/year/2019/tradeflow/Imports/partner/ALL/product/271111 | I9: 2026-10-27
A10: 2020 | B10: 271111 | C10: LNG | D10: 59910.33 | E10: 296302000 | F10: =D10*Settings!$B$7 -> 59910330 | G10: reported | H10: https://wits.worldbank.org/trade/comtrade/en/country/COL/year/2020/tradeflow/Imports/partner/ALL/product/271111 | I10: 2026-10-27
A11: 2021 | B11: 271111 | C11: LNG | D11: 27941.49 | E11: 44406000 | F11: =D11*Settings!$B$7 -> 27941490 | G11: reported | H11: https://wits.worldbank.org/trade/comtrade/en/country/COL/year/2021/tradeflow/Imports/partner/ALL/product/271111 | I11: 2026-10-27
A12: 2021 | B12: 271121 | C12: Natural gas, gaseous | D12: 43.16 | E12: 3843 | F12: =D12*Settings!$B$7 -> 43160 | G12: reported | H12: https://wits.worldbank.org/trade/comtrade/en/country/COL/year/2021/tradeflow/Imports/partner/ALL/product/271121 | I12: 2026-10-27
A13: 2022 | B13: 271111 | C13: LNG | D13: 87550.64 | E13: 60181000 | F13: =D13*Settings!$B$7 -> 87550640 | G13: reported | H13: https://wits.worldbank.org/trade/comtrade/en/country/COL/year/2022/tradeflow/Imports/partner/ALL/product/271111 | I13: 2026-10-27
A14: 2022 | B14: 271121 | C14: Natural gas, gaseous | D14: 84.12 | E14: 4095 | F14: =D14*Settings!$B$7 -> 84120 | G14: reported | H14: https://wits.worldbank.org/trade/comtrade/en/country/COL/year/2022/tradeflow/Imports/partner/ALL/product/271121 | I14: 2026-10-27
A15: 2023 | B15: 271111 | C15: LNG | D15: 441455.97 | F15: =D15*Settings!$B$7 -> 441455970 | G15: missing_not_zero | H15: https://wits.worldbank.org/trade/comtrade/en/country/COL/year/2023/tradeflow/Imports/partner/ALL/product/271111 | I15: 2026-10-27
A16: 2023 | B16: 271121 | C16: Natural gas, gaseous | D16: 4.93 | E16: 5995 | F16: =D16*Settings!$B$7 -> 4930 | G16: reported | H16: https://wits.worldbank.org/trade/comtrade/en/country/COL/year/2023/tradeflow/Imports/partner/ALL/product/271121 | I16: 2026-10-27
A17: 2024 | B17: 271111 | C17: LNG | D17: 945446.54 | E17: 1625300000 | F17: =D17*Settings!$B$7 -> 945446540 | G17: reported | H17: https://wits.worldbank.org/trade/comtrade/en/country/COL/year/2024/tradeflow/Imports/partner/ALL/product/271111 | I17: 2026-10-27
A18: 2024 | B18: 271121 | C18: Natural gas, gaseous | D18: 31.74 | E18: 935 | F18: =D18*Settings!$B$7 -> 31740 | G18: reported | H18: https://wits.worldbank.org/trade/comtrade/en/country/COL/year/2024/tradeflow/Imports/partner/ALL/product/271121 | I18: 2026-10-27
A19: 2025 | B19: 271111 | C19: LNG | D19: 779203.66 | F19: =D19*Settings!$B$7 -> 779203660 | G19: missing_not_zero | H19: https://wits.worldbank.org/trade/comtrade/en/country/COL/year/2025/tradeflow/Imports/partner/ALL/product/271111 | I19: 2026-10-27
A20: 2025 | B20: 271121 | C20: Natural gas, gaseous | D20: 27.57 | F20: =D20*Settings!$B$7 -> 27570 | G20: missing_not_zero | H20: https://wits.worldbank.org/trade/comtrade/en/country/COL/year/2025/tradeflow/Imports/partner/ALL/product/271121 | I20: 2026-10-27

Sheet Partners
A1: PARTNER DETAIL | ANNUAL IMPORTS
A2: Raw partner labels are preserved. The 2025 LNG analysis label for Tanzania is reconciled to Trinidad and Tobago using DANE, and is explicitly flagged. Do not infer liquefaction origin from partner labels.
A6: Year | B6: HS6 | C6: Partner reported | D6: Partner for analysis | E6: Source value (US$ thousands) | F6: CIF value (US$) | G6: Reported quantity (kg) | H6: Quality / reconciliation note | I6: Source URL | J6: Reconciliation URL
A7: 2017 | B7: 271111 | C7: Switzerland | D7: Switzerland | E7: 11925.93 | F7: =E7*Settings!$B$7 -> 11925930 | G7: 38942600 | H7: Reported trade partner. Do not automatically interpret as liquefaction/production origin. | I7: https://wits.worldbank.org/trade/comtrade/en/country/COL/year/2017/tradeflow/Imports/partner/ALL/product/271111
A8: 2018 | B8: 271111 | C8: United States | D8: United States | E8: 39553.93 | F8: =E8*Settings!$B$7 -> 39553930 | G8: 69076600 | I8: https://wits.worldbank.org/trade/comtrade/en/country/COL/year/2018/tradeflow/Imports/partner/ALL/product/271111
A9: 2018 | B9: 271111 | C9: Trinidad and Tobago | D9: Trinidad and Tobago | E9: 36711.02 | F9: =E9*Settings!$B$7 -> 36711020 | G9: 71101100 | I9: https://wits.worldbank.org/trade/comtrade/en/country/COL/year/2018/tradeflow/Imports/partner/ALL/product/271111
A10: 2018 | B10: 271111 | C10: United Kingdom | D10: United Kingdom | E10: 32602.78 | F10: =E10*Settings!$B$7 -> 32602780 | G10: 68334300 | H10: Reported trade partner. Do not automatically interpret as liquefaction/production origin. | I10: https://wits.worldbank.org/trade/comtrade/en/country/COL/year/2018/tradeflow/Imports/partner/ALL/product/271111
A11: 2018 | B11: 271111 | C11: Switzerland | D11: Switzerland | E11: 14878.74 | F11: =E11*Settings!$B$7 -> 14878740 | G11: 31125900 | H11: Reported trade partner. Do not automatically interpret as liquefaction/production origin. | I11: https://wits.worldbank.org/trade/comtrade/en/country/COL/year/2018/tradeflow/Imports/partner/ALL/product/271111
A12: 2018 | B12: 271111 | C12: Peru | D12: Peru | E12: 0.9 | F12: =E12*Settings!$B$7 -> 900 | G12: 14 | I12: https://wits.worldbank.org/trade/comtrade/en/country/COL/year/2018/tradeflow/Imports/partner/ALL/product/271111
A13: 2019 | B13: 271111 | C13: Ireland | D13: Ireland | E13: 27308.73 | F13: =E13*Settings!$B$7 -> 27308730 | G13: 66112400 | H13: Reported trade partner. Do not automatically interpret as liquefaction/production origin. | I13: https://wits.worldbank.org/trade/comtrade/en/country/COL/year/2019/tradeflow/Imports/partner/ALL/product/271111
A14: 2019 | B14: 271111 | C14: United States | D14: United States | E14: 21902.39 | F14: =E14*Settings!$B$7 -> 21902390 | I14: https://wits.worldbank.org/trade/comtrade/en/country/COL/year/2019/tradeflow/Imports/partner/ALL/product/271111
A15: 2019 | B15: 271111 | C15: Trinidad and Tobago | D15: Trinidad and Tobago | E15: 7832.93 | F15: =E15*Settings!$B$7 -> 7832930 | G15: 34111700 | I15: https://wits.worldbank.org/trade/comtrade/en/country/COL/year/2019/tradeflow/Imports/partner/ALL/product/271111
A16: 2020 | B16: 271111 | C16: United Arab Emirates | D16: United Arab Emirates | E16: 21633.89 | F16: =E16*Settings!$B$7 -> 21633890 | G16: 116121000 | H16: Reported trade partner. Do not automatically interpret as liquefaction/production origin. | I16: https://wits.worldbank.org/trade/comtrade/en/country/COL/year/2020/tradeflow/Imports/partner/ALL/product/271111
A17: 2020 | B17: 271111 | C17: United Kingdom | D17: United Kingdom | E17: 20339.8 | F17: =E17*Settings!$B$7 -> 20339800 | G17: 88247200 | H17: Reported trade partner. Do not automatically interpret as liquefaction/production origin. | I17: https://wits.worldbank.org/trade/comtrade/en/country/COL/year/2020/tradeflow/Imports/partner/ALL/product/271111
A18: 2020 | B18: 271111 | C18: Trinidad and Tobago | D18: Trinidad and Tobago | E18: 13410.35 | F18: =E18*Settings!$B$7 -> 13410350 | G18: 70111100 | I18: https://wits.worldbank.org/trade/comtrade/en/country/COL/year/2020/tradeflow/Imports/partner/ALL/product/271111
A19: 2020 | B19: 271111 | C19: United States | D19: United States | E19: 2972.81 | F19: =E19*Settings!$B$7 -> 2972810 | G19: 10708100 | I19: https://wits.worldbank.org/trade/comtrade/en/country/COL/year/2020/tradeflow/Imports/partner/ALL/product/271111
A20: 2020 | B20: 271111 | C20: Switzerland | D20: Switzerland | E20: 1553.47 | F20: =E20*Settings!$B$7 -> 1553470 | G20: 11114600 | H20: Reported trade partner. Do not automatically interpret as liquefaction/production origin. | I20: https://wits.worldbank.org/trade/comtrade/en/country/COL/year/2020/tradeflow/Imports/partner/ALL/product/271111
A21: 2021 | B21: 271111 | C21: United States | D21: United States | E21: 14510.52 | F21: =E21*Settings!$B$7 -> 14510520 | G21: 18165700 | I21: https://wits.worldbank.org/trade/comtrade/en/country/COL/year/2021/tradeflow/Imports/partner/ALL/product/271111
A22: 2021 | B22: 271111 | C22: United Kingdom | D22: United Kingdom | E22: 13422.46 | F22: =E22*Settings!$B$7 -> 13422460 | G22: 26237900 | H22: Reported trade partner. Do not automatically interpret as liquefaction/production origin. | I22: https://wits.worldbank.org/trade/comtrade/en/country/COL/year/2021/tradeflow/Imports/partner/ALL/product/271111
A23: 2021 | B23: 271111 | C23: Canada | D23: Canada | E23: 4.46 | F23: =E23*Settings!$B$7 -> 4460 | G23: 517 | I23: https://wits.worldbank.org/trade/comtrade/en/country/COL/year/2021/tradeflow/Imports/partner/ALL/product/271111
A24: 2021 | B24: 271111 | C24: Bolivia | D24: Bolivia | E24: 4.05 | F24: =E24*Settings!$B$7 -> 4050 | G24: 1815 | I24: https://wits.worldbank.org/trade/comtrade/en/country/COL/year/2021/tradeflow/Imports/partner/ALL/product/271111
A25: 2021 | B25: 271121 | C25: United States | D25: United States | E25: 29.64 | F25: =E25*Settings!$B$7 -> 29640 | G25: 837 | I25: https://wits.worldbank.org/trade/comtrade/en/country/COL/year/2021/tradeflow/Imports/partner/ALL/product/271121
A26: 2021 | B26: 271121 | C26: China | D26: China | E26: 13.51 | F26: =E26*Settings!$B$7 -> 13510 | G26: 3006 | I26: https://wits.worldbank.org/trade/comtrade/en/country/COL/year/2021/tradeflow/Imports/partner/ALL/product/271121
A27: 2022 | B27: 271111 | C27: United States | D27: United States | E27: 87550.64 | F27: =E27*Settings!$B$7 -> 87550640 | G27: 60181000 | I27: https://wits.worldbank.org/trade/comtrade/en/country/COL/year/2022/tradeflow/Imports/partner/ALL/product/271111
A28: 2022 | B28: 271121 | C28: United States | D28: United States | E28: 75.04 | F28: =E28*Settings!$B$7 -> 75040 | G28: 1724 | I28: https://wits.worldbank.org/trade/comtrade/en/country/COL/year/2022/tradeflow/Imports/partner/ALL/product/271121
A29: 2022 | B29: 271121 | C29: China | D29: China | E29: 9.08 | F29: =E29*Settings!$B$7 -> 9080 | G29: 2370 | I29: https://wits.worldbank.org/trade/comtrade/en/country/COL/year/2022/tradeflow/Imports/partner/ALL/product/271121
A30: 2023 | B30: 271111 | C30: United States | D30: United States | E30: 410852.09 | F30: =E30*Settings!$B$7 -> 410852090 | G30: 587226000 | I30: https://wits.worldbank.org/trade/comtrade/en/country/COL/year/2023/tradeflow/Imports/partner/ALL/product/271111
A31: 2023 | B31: 271111 | C31: Trinidad and Tobago | D31: Trinidad and Tobago | E31: 30603.01 | F31: =E31*Settings!$B$7 -> 30603010 | G31: 38373800 | I31: https://wits.worldbank.org/trade/comtrade/en/country/COL/year/2023/tradeflow/Imports/partner/ALL/product/271111
A32: 2023 | B32: 271111 | C32: United Kingdom | D32: United Kingdom | E32: 0.87 | F32: =E32*Settings!$B$7 -> 870 | H32: Reported trade partner. Do not automatically interpret as liquefaction/production origin. | I32: https://wits.worldbank.org/trade/comtrade/en/country/COL/year/2023/tradeflow/Imports/partner/ALL/product/271111
A33: 2023 | B33: 271121 | C33: United States | D33: United States | E33: 4.93 | F33: =E33*Settings!$B$7 -> 4930 | G33: 5995 | I33: https://wits.worldbank.org/trade/comtrade/en/country/COL/year/2023/tradeflow/Imports/partner/ALL/product/271121
A34: 2024 | B34: 271111 | C34: United States | D34: United States | E34: 771978.25 | F34: =E34*Settings!$B$7 -> 771978250 | G34: 1383020000 | I34: https://wits.worldbank.org/trade/comtrade/en/country/COL/year/2024/tradeflow/Imports/partner/ALL/product/271111
A35: 2024 | B35: 271111 | C35: Trinidad and Tobago | D35: Trinidad and Tobago | E35: 134542.94 | F35: =E35*Settings!$B$7 -> 134542940 | G35: 192276000 | I35: https://wits.worldbank.org/trade/comtrade/en/country/COL/year/2024/tradeflow/Imports/partner/ALL/product/271111
A36: 2024 | B36: 271111 | C36: United Kingdom | D36: United Kingdom | E36: 38925.35 | F36: =E36*Settings!$B$7 -> 38925350 | G36: 50000800 | H36: Reported trade partner. Do not automatically interpret as liquefaction/production origin. | I36: https://wits.worldbank.org/trade/comtrade/en/country/COL/year/2024/tradeflow/Imports/partner/ALL/product/271111
A37: 2024 | B37: 271121 | C37: United States | D37: United States | E37: 25.29 | F37: =E37*Settings!$B$7 -> 25290 | G37: 392 | I37: https://wits.worldbank.org/trade/comtrade/en/country/COL/year/2024/tradeflow/Imports/partner/ALL/product/271121
A38: 2024 | B38: 271121 | C38: Unspecified | D38: Unspecified | E38: 6.45 | F38: =E38*Settings!$B$7 -> 6450 | G38: 543 | I38: https://wits.worldbank.org/trade/comtrade/en/country/COL/year/2024/tradeflow/Imports/partner/ALL/product/271121
A39: 2025 | B39: 271111 | C39: Tanzania | D39: Trinidad and Tobago | E39: 390808.22 | F39: =E39*Settings!$B$7 -> 390808220 | G39: 597442000 | H39: Raw WITS label Tanzania retained. Analysis label reconciled to DANE Dec-2025 p11 (US$390.8m). This is an analyst reconciliation, not an upstream correction. | I39: https://wits.worldbank.org/trade/comtrade/en/country/COL/year/2025/tradeflow/Imports/partner/ALL/product/271111 | J39: https://www.dane.gov.co/files/operaciones/IMP/bol-IMP-dic2025.pdf
A40: 2025 | B40: 271111 | C40: United States | D40: United States | E40: 388390.81 | F40: =E40*Settings!$B$7 -> 388390810 | I40: https://wits.worldbank.org/trade/comtrade/en/country/COL/year/2025/tradeflow/Imports/partner/ALL/product/271111
A41: 2025 | B41: 271111 | C41: United Kingdom | D41: United Kingdom | E41: 4.63 | F41: =E41*Settings!$B$7 -> 4630 | G41: 6939 | H41: Reported trade partner. Do not automatically interpret as liquefaction/production origin. | I41: https://wits.worldbank.org/trade/comtrade/en/country/COL/year/2025/tradeflow/Imports/partner/ALL/product/271111
A42: 2025 | B42: 271121 | C42: United States | D42: United States | E42: 25.28 | F42: =E42*Settings!$B$7 -> 25280 | I42: https://wits.worldbank.org/trade/comtrade/en/country/COL/year/2025/tradeflow/Imports/partner/ALL/product/271121
A43: 2025 | B43: 271121 | C43: Australia | D43: Australia | E43: 2.29 | F43: =E43*Settings!$B$7 -> 2290 | I43: https://wits.worldbank.org/trade/comtrade/en/country/COL/year/2025/tradeflow/Imports/partner/ALL/product/271121

Sheet BMC scenario
A1: BMC | VISIBLE FORWARD SCENARIO
A2: Exact table cells from the user screenshot: UPME + OEF XM. This is total supply versus demand, NOT projected LNG imports. Yellow domestic-supply inputs are intentionally blank; price is an illustrative assumption.
A6: Month | B6: Supply (MBtu/day) | C6: Demand projection (MBtu/day) | D6: Published margin (MBtu/day) | E6: Calculated margin (MBtu/day) | F6: Margin check | G6: Usable domestic supply (input, MBtu/day) | H6: Residual import need (MBtu/day) | I6: Border LNG price (US$/MMBtu) | J6: Days in month | K6: Indicative monthly LNG bill (US$ million) | L6: Scenario | M6: Source / provenance
A7: 46296 | B7: 1144175 | C7: 1205885 | D7: -61710 | E7: =B7-C7 -> -61710 | F7: =IF(E7=D7,"PASS","REVIEW") -> PASS | H7: =IF(ISNUMBER(G7),MAX(0,C7-G7),"") | I7: =Settings!$B$10 -> 12 | J7: =DAY(EOMONTH(A7,0)) -> 31 | K7: =IF(AND(ISNUMBER(G7),G7>=0),H7*I7*J7/Settings!$B$8,"") | L7: UPME + OEF XM | M7: User screenshot: exact visible table; https://www.bmcbec.com.co/
A8: 46327 | B8: 1257285 | C8: 1184705 | D8: 72580 | E8: =B8-C8 -> 72580 | F8: =IF(E8=D8,"PASS","REVIEW") -> PASS | H8: =IF(ISNUMBER(G8),MAX(0,C8-G8),"") | I8: =Settings!$B$10 -> 12 | J8: =DAY(EOMONTH(A8,0)) -> 30 | K8: =IF(AND(ISNUMBER(G8),G8>=0),H8*I8*J8/Settings!$B$8,"") | L8: UPME + OEF XM | M8: User screenshot: exact visible table; https://www.bmcbec.com.co/
A9: 46357 | B9: 1245033 | C9: 1293349 | D9: -48316 | E9: =B9-C9 -> -48316 | F9: =IF(E9=D9,"PASS","REVIEW") -> PASS | H9: =IF(ISNUMBER(G9),MAX(0,C9-G9),"") | I9: =Settings!$B$10 -> 12 | J9: =DAY(EOMONTH(A9,0)) -> 31 | K9: =IF(AND(ISNUMBER(G9),G9>=0),H9*I9*J9/Settings!$B$8,"") | L9: UPME + OEF XM | M9: User screenshot: exact visible table; https://www.bmcbec.com.co/
A10: 46388 | B10: 1234062 | C10: 1282217 | D10: -48155 | E10: =B10-C10 -> -48155 | F10: =IF(E10=D10,"PASS","REVIEW") -> PASS | H10: =IF(ISNUMBER(G10),MAX(0,C10-G10),"") | I10: =Settings!$B$10 -> 12 | J10: =DAY(EOMONTH(A10,0)) -> 31 | K10: =IF(AND(ISNUMBER(G10),G10>=0),H10*I10*J10/Settings!$B$8,"") | L10: UPME + OEF XM | M10: User screenshot: exact visible table; https://www.bmcbec.com.co/
A11: 46419 | B11: 1261486 | C11: 1301626 | D11: -40140 | E11: =B11-C11 -> -40140 | F11: =IF(E11=D11,"PASS","REVIEW") -> PASS | H11: =IF(ISNUMBER(G11),MAX(0,C11-G11),"") | I11: =Settings!$B$10 -> 12 | J11: =DAY(EOMONTH(A11,0)) -> 28 | K11: =IF(AND(ISNUMBER(G11),G11>=0),H11*I11*J11/Settings!$B$8,"") | L11: UPME + OEF XM | M11: User screenshot: exact visible table; https://www.bmcbec.com.co/
A12: 46447 | B12: 1268968 | C12: 1317922 | D12: -48954 | E12: =B12-C12 -> -48954 | F12: =IF(E12=D12,"PASS","REVIEW") -> PASS | H12: =IF(ISNUMBER(G12),MAX(0,C12-G12),"") | I12: =Settings!$B$10 -> 12 | J12: =DAY(EOMONTH(A12,0)) -> 31 | K12: =IF(AND(ISNUMBER(G12),G12>=0),H12*I12*J12/Settings!$B$8,"") | L12: UPME + OEF XM | M12: User screenshot: exact visible table; https://www.bmcbec.com.co/
A13: 46478 | B13: 1267109 | C13: 1104530 | D13: 162579 | E13: =B13-C13 -> 162579 | F13: =IF(E13=D13,"PASS","REVIEW") -> PASS | H13: =IF(ISNUMBER(G13),MAX(0,C13-G13),"") | I13: =Settings!$B$10 -> 12 | J13: =DAY(EOMONTH(A13,0)) -> 30 | K13: =IF(AND(ISNUMBER(G13),G13>=0),H13*I13*J13/Settings!$B$8,"") | L13: UPME + OEF XM | M13: User screenshot: exact visible table; https://www.bmcbec.com.co/
A14: 46508 | B14: 1263599 | C14: 1089386 | D14: 174213 | E14: =B14-C14 -> 174213 | F14: =IF(E14=D14,"PASS","REVIEW") -> PASS | H14: =IF(ISNUMBER(G14),MAX(0,C14-G14),"") | I14: =Settings!$B$10 -> 12 | J14: =DAY(EOMONTH(A14,0)) -> 31 | K14: =IF(AND(ISNUMBER(G14),G14>=0),H14*I14*J14/Settings!$B$8,"") | L14: UPME + OEF XM | M14: User screenshot: exact visible table; https://www.bmcbec.com.co/
A15: 46539 | B15: 1267572 | C15: 1186340 | D15: 81232 | E15: =B15-C15 -> 81232 | F15: =IF(E15=D15,"PASS","REVIEW") -> PASS | H15: =IF(ISNUMBER(G15),MAX(0,C15-G15),"") | I15: =Settings!$B$10 -> 12 | J15: =DAY(EOMONTH(A15,0)) -> 30 | K15: =IF(AND(ISNUMBER(G15),G15>=0),H15*I15*J15/Settings!$B$8,"") | L15: UPME + OEF XM | M15: User screenshot: exact visible table; https://www.bmcbec.com.co/
A16: 46569 | B16: 1277866 | C16: 1133719 | D16: 144147 | E16: =B16-C16 -> 144147 | F16: =IF(E16=D16,"PASS","REVIEW") -> PASS | H16: =IF(ISNUMBER(G16),MAX(0,C16-G16),"") | I16: =Settings!$B$10 -> 12 | J16: =DAY(EOMONTH(A16,0)) -> 31 | K16: =IF(AND(ISNUMBER(G16),G16>=0),H16*I16*J16/Settings!$B$8,"") | L16: UPME + OEF XM | M16: User screenshot: exact visible table; https://www.bmcbec.com.co/
A17: 46600 | B17: 1281951 | C17: 1127004 | D17: 154947 | E17: =B17-C17 -> 154947 | F17: =IF(E17=D17,"PASS","REVIEW") -> PASS | H17: =IF(ISNUMBER(G17),MAX(0,C17-G17),"") | I17: =Settings!$B$10 -> 12 | J17: =DAY(EOMONTH(A17,0)) -> 31 | K17: =IF(AND(ISNUMBER(G17),G17>=0),H17*I17*J17/Settings!$B$8,"") | L17: UPME + OEF XM | M17: User screenshot: exact visible table; https://www.bmcbec.com.co/
A18: 46631 | B18: 1282211 | C18: 989533 | D18: 292678 | E18: =B18-C18 -> 292678 | F18: =IF(E18=D18,"PASS","REVIEW") -> PASS | H18: =IF(ISNUMBER(G18),MAX(0,C18-G18),"") | I18: =Settings!$B$10 -> 12 | J18: =DAY(EOMONTH(A18,0)) -> 30 | K18: =IF(AND(ISNUMBER(G18),G18>=0),H18*I18*J18/Settings!$B$8,"") | L18: UPME + OEF XM | M18: User screenshot: exact visible table; https://www.bmcbec.com.co/
... A20: 46692 | B20: 1312109 | C20: 986976 | D20: 325133 | E20: =B20-C20 -> 325133 | F20: =IF(E20=D20,"PASS","REVIEW") -> PASS | H20: =IF(ISNUMBER(G20),MAX(0,C20-G20),"") | I20: =Settings!$B$10 -> 12 | J20: =DAY(EOMONTH(A20,0)) -> 30 | K20: =IF(AND(ISNUMBER(G20),G20>=0),H20*I20*J20/Settings!$B$8,"") | L20: UPME + OEF XM | M20: User screenshot: exact visible table; https://www.bmcbec.com.co/
A23: Residual import need = max(0, demand - usable domestic supply). It is uncapped demand for imported gas, not contracted cargoes. Total supply in column B already includes import-related components; never enter B into G.
A25: Only the 14 displayed rows were transcribed. No 2028 values or terminal-specific volumes were guessed from the stacked bars. Scenario prices and actual customs costs remain separate.

Sheet Selected monthly
A1: SELECTED MONTHLY | NOT NATIONAL TOTALS
A2: Only two LNG observations for Trinidad and Tobago from DANE August 2026 bulletin, p. 9. These are provisional, rounded and partner-specific; they are NOT a complete monthly series.
A6: Month | B6: Origin partner | C6: Product label | D6: CIF value (US$ million) | E6: CIF value (US$) | F6: Coverage | G6: Source URL | H6: Source page
A7: 45870 | B7: Trinidad and Tobago | C7: Gas natural licuado | D7: 21.4 | E7: =D7*Settings!$B$8 -> 21400000 | F7: One partner only - not national total | G7: https://www.dane.gov.co/files/operaciones/IMP/bol-IMP-ago2026.pdf | H7: 9
A8: 46235 | B8: Trinidad and Tobago | C8: Gas natural licuado | D8: 195.8 | E8: =D8*Settings!$B$8 -> 195800000 | F8: One partner only - not national total | G8: https://www.dane.gov.co/files/operaciones/IMP/bol-IMP-ago2026.pdf | H8: 9
A11: Do not combine these two partner observations with national totals as though they were the same series. This sheet does not establish the 2026 national LNG import bill.

Sheet Monthly imports
A1: MONTHLY CUSTOMS | NOT LOADED
A2: No national monthly customs data were downloaded. This schema is intentionally empty. The supplied loader reads DANE archives and exports monthly partner / national-product CSVs, SQLite and a separate Excel workbook.
A6: Month | B6: HS6 | C6: HS10 | D6: Origin code | E6: Country-code scheme | F6: Origin name | G6: FOB (US$) | H6: CIF (US$) | I6: Net weight (kg) | J6: Source file | K6: Source URL
A9: ZERO NATIONAL MONTHLY ROWS LOADED. Missing observations have not been fabricated or spread evenly across months.

Sheet Checks
A1: VALIDATION | RECONCILIATION
A2: Dollar checks compare WITS world totals against their partner rows. Small differences arise because WITS values are rounded to US$10. Missing quantities are not imputed.
A6: Year | B6: HS6 | C6: World CIF (US$) | D6: Sum of partners (US$) | E6: Residual (US$) | F6: Tolerance (US$) | G6: Check | H6: Quantity missing? | I6: Source URL
A7: 2017 | B7: 271111 | C7: ='Annual raw'!F7 -> 11925930 | D7: =SUMIFS(Partners!$F$7:$F$43,Partners!$A$7:$A$43,A7,Partners!$B$7:$B$43,B7) -> 11925930 | E7: =C7-D7 -> 0 | F7: =Settings!$B$11 -> 50 | G7: =IF(ABS(E7)<=F7,"PASS","REVIEW") -> PASS | H7: NO | I7: https://wits.worldbank.org/trade/comtrade/en/country/COL/year/2017/tradeflow/Imports/partner/ALL/product/271111
A8: 2018 | B8: 271111 | C8: ='Annual raw'!F8 -> 123747360 | D8: =SUMIFS(Partners!$F$7:$F$43,Partners!$A$7:$A$43,A8,Partners!$B$7:$B$43,B8) -> 123747370 | E8: =C8-D8 -> -10 | F8: =Settings!$B$11 -> 50 | G8: =IF(ABS(E8)<=F8,"PASS","REVIEW") -> PASS | H8: NO | I8: https://wits.worldbank.org/trade/comtrade/en/country/COL/year/2018/tradeflow/Imports/partner/ALL/product/271111
A9: 2019 | B9: 271111 | C9: ='Annual raw'!F9 -> 57044060 | D9: =SUMIFS(Partners!$F$7:$F$43,Partners!$A$7:$A$43,A9,Partners!$B$7:$B$43,B9) -> 57044050 | E9: =C9-D9 -> 10 | F9: =Settings!$B$11 -> 50 | G9: =IF(ABS(E9)<=F9,"PASS","REVIEW") -> PASS | H9: YES | I9: https://wits.worldbank.org/trade/comtrade/en/country/COL/year/2019/tradeflow/Imports/partner/ALL/product/271111
A10: 2020 | B10: 271111 | C10: ='Annual raw'!F10 -> 59910330 | D10: =SUMIFS(Partners!$F$7:$F$43,Partners!$A$7:$A$43,A10,Partners!$B$7:$B$43,B10) -> 59910320 | E10: =C10-D10 -> 10 | F10: =Settings!$B$11 -> 50 | G10: =IF(ABS(E10)<=F10,"PASS","REVIEW") -> PASS | H10: NO | I10: https://wits.worldbank.org/trade/comtrade/en/country/COL/year/2020/tradeflow/Imports/partner/ALL/product/271111
A11: 2021 | B11: 271111 | C11: ='Annual raw'!F11 -> 27941490 | D11: =SUMIFS(Partners!$F$7:$F$43,Partners!$A$7:$A$43,A11,Partners!$B$7:$B$43,B11) -> 27941490 | E11: =C11-D11 -> 0 | F11: =Settings!$B$11 -> 50 | G11: =IF(ABS(E11)<=F11,"PASS","REVIEW") -> PASS | H11: NO | I11: https://wits.worldbank.org/trade/comtrade/en/country/COL/year/2021/tradeflow/Imports/partner/ALL/product/271111
A12: 2021 | B12: 271121 | C12: ='Annual raw'!F12 -> 43160 | D12: =SUMIFS(Partners!$F$7:$F$43,Partners!$A$7:$A$43,A12,Partners!$B$7:$B$43,B12) -> 43150 | E12: =C12-D12 -> 10 | F12: =Settings!$B$11 -> 50 | G12: =IF(ABS(E12)<=F12,"PASS","REVIEW") -> PASS | H12: NO | I12: https://wits.worldbank.org/trade/comtrade/en/country/COL/year/2021/tradeflow/Imports/partner/ALL/product/271121
A13: 2022 | B13: 271111 | C13: ='Annual raw'!F13 -> 87550640 | D13: =SUMIFS(Partners!$F$7:$F$43,Partners!$A$7:$A$43,A13,Partners!$B$7:$B$43,B13) -> 87550640 | E13: =C13-D13 -> 0 | F13: =Settings!$B$11 -> 50 | G13: =IF(ABS(E13)<=F13,"PASS","REVIEW") -> PASS | H13: NO | I13: https://wits.worldbank.org/trade/comtrade/en/country/COL/year/2022/tradeflow/Imports/partner/ALL/product/271111
A14: 2022 | B14: 271121 | C14: ='Annual raw'!F14 -> 84120 | D14: =SUMIFS(Partners!$F$7:$F$43,Partners!$A$7:$A$43,A14,Partners!$B$7:$B$43,B14) -> 84120 | E14: =C14-D14 -> 0 | F14: =Settings!$B$11 -> 50 | G14: =IF(ABS(E14)<=F14,"PASS","REVIEW") -> PASS | H14: NO | I14: https://wits.worldbank.org/trade/comtrade/en/country/COL/year/2022/tradeflow/Imports/partner/ALL/product/271121
A15: 2023 | B15: 271111 | C15: ='Annual raw'!F15 -> 441455970 | D15: =SUMIFS(Partners!$F$7:$F$43,Partners!$A$7:$A$43,A15,Partners!$B$7:$B$43,B15) -> 441455970 | E15: =C15-D15 -> 0 | F15: =Settings!$B$11 -> 50 | G15: =IF(ABS(E15)<=F15,"PASS","REVIEW") -> PASS | H15: YES | I15: https://wits.worldbank.org/trade/comtrade/en/country/COL/year/2023/tradeflow/Imports/partner/ALL/product/271111
A16: 2023 | B16: 271121 | C16: ='Annual raw'!F16 -> 4930 | D16: =SUMIFS(Partners!$F$7:$F$43,Partners!$A$7:$A$43,A16,Partners!$B$7:$B$43,B16) -> 4930 | E16: =C16-D16 -> 0 | F16: =Settings!$B$11 -> 50 | G16: =IF(ABS(E16)<=F16,"PASS","REVIEW") -> PASS | H16: NO | I16: https://wits.worldbank.org/trade/comtrade/en/country/COL/year/2023/tradeflow/Imports/partner/ALL/product/271121
A17: 2024 | B17: 271111 | C17: ='Annual raw'!F17 -> 945446540 | D17: =SUMIFS(Partners!$F$7:$F$43,Partners!$A$7:$A$43,A17,Partners!$B$7:$B$43,B17) -> 945446540 | E17: =C17-D17 -> 0 | F17: =Settings!$B$11 -> 50 | G17: =IF(ABS(E17)<=F17,"PASS","REVIEW") -> PASS | H17: NO | I17: https://wits.worldbank.org/trade/comtrade/en/country/COL/year/2024/tradeflow/Imports/partner/ALL/product/271111
A18: 2024 | B18: 271121 | C18: ='Annual raw'!F18 -> 31740 | D18: =SUMIFS(Partners!$F$7:$F$43,Partners!$A$7:$A$43,A18,Partners!$B$7:$B$43,B18) -> 31740 | E18: =C18-D18 -> 0 | F18: =Settings!$B$11 -> 50 | G18: =IF(ABS(E18)<=F18,"PASS","REVIEW") -> PASS | H18: NO | I18: https://wits.worldbank.org/trade/comtrade/en/country/COL/year/2024/tradeflow/Imports/partner/ALL/product/271121
... A20: 2025 | B20: 271121 | C20: ='Annual raw'!F20 -> 27570 | D20: =SUMIFS(Partners!$F$7:$F$43,Partners!$A$7:$A$43,A20,Partners!$B$7:$B$43,B20) -> 27570 | E20: =C20-D20 -> 0 | F20: =Settings!$B$11 -> 50 | G20: =IF(ABS(E20)<=F20,"PASS","REVIEW") -> PASS | H20: YES | I20: https://wits.worldbank.org/trade/comtrade/en/country/COL/year/2025/tradeflow/Imports/partner/ALL/product/271121
A23: Additional checks: 14/14 BMC margins reconcile exactly. No national monthly customs observations were loaded. World LNG quantity is missing for 2019, 2023 and 2025.

Sheet Sources
A1: SOURCE REGISTER | AUDIT TRAIL
A2: URLs and retrieval status are retained. Public annual tables were read; this is not a transaction-level DANE archive extraction.
A6: Source ID | B6: Publisher | C6: Document / table | D6: Source URL | E6: Accessed | F6: Scope | G6: Retrieval status
A7: WITS_271111_2017 | B7: World Bank WITS / UN Comtrade | C7: Colombia imports: HS 271111, 2017 | D7: https://wits.worldbank.org/trade/comtrade/en/country/COL/year/2017/tradeflow/Imports/partner/ALL/product/271111 | E7: 2026-10-27 | F7: Annual public summary; monetary values displayed to US$10 precision | G7: Table retrieved; not customs microdata
A8: WITS_271111_2018 | B8: World Bank WITS / UN Comtrade | C8: Colombia imports: HS 271111, 2018 | D8: https://wits.worldbank.org/trade/comtrade/en/country/COL/year/2018/tradeflow/Imports/partner/ALL/product/271111 | E8: 2026-10-27 | F8: Annual public summary; monetary values displayed to US$10 precision | G8: Table retrieved; not customs microdata
A9: WITS_271111_2019 | B9: World Bank WITS / UN Comtrade | C9: Colombia imports: HS 271111, 2019 | D9: https://wits.worldbank.org/trade/comtrade/en/country/COL/year/2019/tradeflow/Imports/partner/ALL/product/271111 | E9: 2026-10-27 | F9: Annual public summary; monetary values displayed to US$10 precision | G9: Table retrieved; not customs microdata
A10: WITS_271111_2020 | B10: World Bank WITS / UN Comtrade | C10: Colombia imports: HS 271111, 2020 | D10: https://wits.worldbank.org/trade/comtrade/en/country/COL/year/2020/tradeflow/Imports/partner/ALL/product/271111 | E10: 2026-10-27 | F10: Annual public summary; monetary values displayed to US$10 precision | G10: Table retrieved; not customs microdata
A11: WITS_271111_2021 | B11: World Bank WITS / UN Comtrade | C11: Colombia imports: HS 271111, 2021 | D11: https://wits.worldbank.org/trade/comtrade/en/country/COL/year/2021/tradeflow/Imports/partner/ALL/product/271111 | E11: 2026-10-27 | F11: Annual public summary; monetary values displayed to US$10 precision | G11: Table retrieved; not customs microdata
A12: WITS_271121_2021 | B12: World Bank WITS / UN Comtrade | C12: Colombia imports: HS 271121, 2021 | D12: https://wits.worldbank.org/trade/comtrade/en/country/COL/year/2021/tradeflow/Imports/partner/ALL/product/271121 | E12: 2026-10-27 | F12: Annual public summary; monetary values displayed to US$10 precision | G12: Table retrieved; not customs microdata
A13: WITS_271111_2022 | B13: World Bank WITS / UN Comtrade | C13: Colombia imports: HS 271111, 2022 | D13: https://wits.worldbank.org/trade/comtrade/en/country/COL/year/2022/tradeflow/Imports/partner/ALL/product/271111 | E13: 2026-10-27 | F13: Annual public summary; monetary values displayed to US$10 precision | G13: Table retrieved; not customs microdata
A14: WITS_271121_2022 | B14: World Bank WITS / UN Comtrade | C14: Colombia imports: HS 271121, 2022 | D14: https://wits.worldbank.org/trade/comtrade/en/country/COL/year/2022/tradeflow/Imports/partner/ALL/product/271121 | E14: 2026-10-27 | F14: Annual public summary; monetary values displayed to US$10 precision | G14: Table retrieved; not customs microdata
A15: WITS_271111_2023 | B15: World Bank WITS / UN Comtrade | C15: Colombia imports: HS 271111, 2023 | D15: https://wits.worldbank.org/trade/comtrade/en/country/COL/year/2023/tradeflow/Imports/partner/ALL/product/271111 | E15: 2026-10-27 | F15: Annual public summary; monetary values displayed to US$10 precision | G15: Table retrieved; not customs microdata
A16: WITS_271121_2023 | B16: World Bank WITS / UN Comtrade | C16: Colombia imports: HS 271121, 2023 | D16: https://wits.worldbank.org/trade/comtrade/en/country/COL/year/2023/tradeflow/Imports/partner/ALL/product/271121 | E16: 2026-10-27 | F16: Annual public summary; monetary values displayed to US$10 precision | G16: Table retrieved; not customs microdata
A17: WITS_271111_2024 | B17: World Bank WITS / UN Comtrade | C17: Colombia imports: HS 271111, 2024 | D17: https://wits.worldbank.org/trade/comtrade/en/country/COL/year/2024/tradeflow/Imports/partner/ALL/product/271111 | E17: 2026-10-27 | F17: Annual public summary; monetary values displayed to US$10 precision | G17: Table retrieved; not customs microdata
... A27: BMC_LOGIN | B27: BMC | C27: BI Gas portal | D27: https://www.bmcbec.com.co/cuadros-power-bi/inicio | E27: 2026-10-27 | F27: Public link redirected to login in this session | G27: No terminal-level time series exported

Sheet Dictionary
A1: DATA DICTIONARY | USE AND LIMITS
A2: Trade values, physical supply and forward scenarios have different units and scopes. Keep those distinctions when building graphs or estimating the external-account impact.
A6: Dataset / field | B6: Definition | C6: Unit / coding | D6: Treatment / limitation
A7: Annual world / partner | B7: WITS public annual summaries; world records and partner records are separate. | C7: Calendar year; HS6 | D7: Do not add world totals to countries. This is not declaration-level microdata.
A8: HS 271111 / 2711110000 | B8: Natural gas, liquefied (LNG). | C8: HS6 / Colombian HS10 | D8: Used for the LNG series. LPG is excluded.
A9: HS 271121 / 2711210000 | B9: Natural gas in gaseous state. | C9: HS6 / Colombian HS10 | D9: Separate from LNG. 2017-2020 were not retrieved in this extraction.
A10: CIF value | B10: Customs value including cost, insurance and freight. | C10: US$ | D10: Annual WITS values are CIF import values; do not use as exact FOB trade-balance contributions.
A11: FOB value | B11: Value excluding international freight and insurance. | C11: US$; DANE field VAFODO | D11: Required for an exact comparison with the FOB merchandise-trade balance. Not available in the populated annual tables.
A12: Reported quantity | B12: WITS quantity field, where provided in kg. | C12: kg; converted to metric tonnes | D12: Missing quantities remain null. Do not sum incomplete partners into a world quantity.
A13: CIF unit value | B13: CIF dollar value divided by reported quantity in tonnes. | C13: US$/tonne | D13: Not a spot LNG price or a domestic tariff. Very small gaseous-gas trade may be non-bulk shipments.
A14: Partner reported | B14: Country label exactly as displayed by WITS. | C14: Text | D14: May not identify the liquefaction country. Labels such as Switzerland and Ireland should not be relabelled without evidence.
A15: Partner for analysis | B15: Reported label except the flagged 2025 LNG reconciliation. | C15: Text | D15: Tanzania -> Trinidad and Tobago is supported by DANE December 2025 p11. Raw label remains available.
A16: FECH | B16: DANE date field; dictionary example 2501. | C16: YYMM, e.g. 2501 = January 2025 | D16: Loader also supports YYYYMM and common explicit date formats; ambiguous dates fail rather than silently convert.
A17: NABAN | B17: Colombian customs commodity code. | C17: 10-digit text | D17: Keep as text; filter exactly 2711110000 / 2711210000.
... A24: Coverage / missing | B24: Absent cells are not assumed zero. | C24: null / blank | D24: No annual-to-monthly interpolation; no terminal-volume estimates from pixels; no fabricated 2026 national totals.

Sheet Settings
A1: SETTINGS | CONVERSIONS AND INPUTS
A2: Blue numeric cells are editable assumptions. Unit factors are constants; the price is an illustration, not a market forecast.
A6: Setting | B6: Value | C6: Meaning / source
A7: US$ thousands to US$ | B7: 1000 | C7: Exact unit conversion.
A8: US$ to US$ million | B8: 1000000 | C8: Exact unit conversion.
A9: kg per metric tonne | B9: 1000 | C9: Exact unit conversion.
A10: Illustrative LNG border price | B10: 12 | C10: US$/MMBtu; analyst input only, not observed or forecast.
A11: Published-value rounding tolerance | B11: 50 | C11: US$; allows small rounded partner/world differences.
