Workbook

Sheet Read me
A1: COLOMBIA | NATURAL GAS IMPORTS
A2: Updated 27 October 2026: monthly DIAN screenshot observations added. Annual CIF history, signed monthly FOB data and BMC scenarios remain separate.
A5: LNG imports: 2025, CIF | D5: Annual LNG coverage | G5: Monthly screenshot observations
A6: ='Annual imports'!E15 -> 779.20366 | D6: 2017-2025 | G6: 20 ROWS / REVIEW
A9: New: 2025/2026 monthly screenshot rows are available. Product/flow filters are cropped; 2025 displayed totals do not reconcile. Bulk national customs archives remain unloaded.
A12: START WITH MONTHLY DASHBOARD
A13: January-August C-labelled comparison, three editable charts and explicit warnings. Historical charts remain on Charts.
A15: USE MONTHLY COMPARISON / MONTHLY LONG
A16: Ten paired months and 20 year-month observations, with original signs, absolute magnitudes, units, source links and row-status metadata.
A18: KEEP THE BMC SCENARIO SEPARATE
A19: 14 exact visible rows from October 2026 to November 2027. Only domestic supply inputs, not total supply, can be used to infer residual import needs.
A21: KEEP RAW DATA AND CHECKS
A22: DIAN raw retains published totals. Monthly checks flags the 2025 gaps; no fabricated months, hidden adjustments or final-data claims.
A24: CONFIRM FILTERS BEFORE LNG-SPECIFIC INFERENCE
A25: Product HS code, national coverage and import-versus-balance selection are not visible. October 2026 is incomplete. Do not splice FOB to CIF.
A28: Source attribution: World Bank WITS / UN Comtrade; DIAN-DANE; BMC screenshot supplied by the user. Fuente: Departamento Administrativo Nacional de Estadistica: www.dane.gov.co

Sheet Monthly dashboard
A1: MONTHLY UPDATE | DIAN SCREENSHOTS
A2: User-provided monthly rows for 2025 and 2026. Headline comparison uses January-August, labelled C. Values are display magnitudes; product and flow filters are not visible.
A5: FOB MAGNITUDE INCREASE | JAN-AUG | D5: NET-WEIGHT MAGNITUDE GROWTH | G5: FOB / WEIGHT RATIO GROWTH
A6: ='Period analysis'!D7 -> 443.56 | D6: ='Period analysis'!H7 -> 0.5498332 | G6: ='Period analysis'!K7 -> 0.13786957
A9: Scope warning: the cropped screenshots do not show the HS code or flow selection. Negative values may represent trade balance. Figures below are magnitudes, not independently verified gross imports.
A66: Do not use the dashboard total as a matched Jan-Oct 2025 total: it exceeds the visible months by USD 33.37m and 69.66m kg. See Monthly checks.
A68: Start with Monthly comparison for charts, Monthly long for imports into software, and Period analysis for the value/weight decomposition and macro scale comparison.

Sheet DIAN raw
A1: DIAN | EXACT SCREENSHOT TRANSCRIPTION
A2: Negative signs, published percentages and non-reconciling totals are retained. Units follow DIAN documentation: USD millions and million kg. Product/flow selections and extraction cutoff are not shown.
A6: Month no. | B6: Month label | C6: FOB 2025 (USD m), signed | D6: FOB 2026 (USD m), signed | E6: FOB YoY, displayed | F6: Weight 2025 (m kg), signed | G6: Weight 2026 (m kg), signed | H6: Weight YoY, displayed | I6: Row status | J6: Quality / scope note | K6: Source URL | L6: FOB evidence | M6: Weight evidence
A7: 1 | B7: 01 - Enero | C7: -78.16 | D7: -68.84 | E7: -0.1192 | F7: -120.15 | G7: -149.79 | H7: 0.247 | I7: C | J7: Product/flow filter not visible; row status is not an independently verified status for each year. | K7: https://www.dian.gov.co/dian/cifras/Paginas/EstadisticasComEx.aspx | L7: evidence/dian_fob.png | M7: evidence/dian_weight.png
A8: 2 | B8: 02 - Febrero | C8: -61.47 | D8: -79.94 | E8: 0.3004 | F8: -86.44 | G8: -167.11 | H8: 0.933 | I8: C | J8: Product/flow filter not visible; row status is not an independently verified status for each year. | K8: https://www.dian.gov.co/dian/cifras/Paginas/EstadisticasComEx.aspx | L8: evidence/dian_fob.png | M8: evidence/dian_weight.png
A9: 3 | B9: 03 - Marzo | C9: -64.28 | D9: -77.95 | E9: 0.2127 | F9: -97.89 | G9: -155.46 | H9: 0.588 | I9: C | J9: Product/flow filter not visible; row status is not an independently verified status for each year. | K9: https://www.dian.gov.co/dian/cifras/Paginas/EstadisticasComEx.aspx | L9: evidence/dian_fob.png | M9: evidence/dian_weight.png
A10: 4 | B10: 04 - Abril | C10: -108.5 | D10: -120.08 | E10: 0.1067 | F10: -203.86 | G10: -184.91 | H10: -0.093 | I10: C | J10: Product/flow filter not visible; row status is not an independently verified status for each year. | K10: https://www.dian.gov.co/dian/cifras/Paginas/EstadisticasComEx.aspx | L10: evidence/dian_fob.png | M10: evidence/dian_weight.png
A11: 5 | B11: 05 - Mayo | C11: -55.22 | D11: -144.8 | E11: 1.6221 | F11: -105.23 | G11: -224.59 | H11: 1.134 | I11: C | J11: Product/flow filter not visible; row status is not an independently verified status for each year. | K11: https://www.dian.gov.co/dian/cifras/Paginas/EstadisticasComEx.aspx | L11: evidence/dian_fob.png | M11: evidence/dian_weight.png
A12: 6 | B12: 06 - Junio | C12: -64.75 | D12: -126.88 | E12: 0.9595 | F12: -118.74 | G12: -172.54 | H12: 0.453 | I12: C | J12: Product/flow filter not visible; row status is not an independently verified status for each year. | K12: https://www.dian.gov.co/dian/cifras/Paginas/EstadisticasComEx.aspx | L12: evidence/dian_fob.png | M12: evidence/dian_weight.png
A13: 7 | B13: 07 - Julio | C13: -91.17 | D13: -203.21 | E13: 1.229 | F13: -172.57 | G13: -294.84 | H13: 0.708 | I13: C | J13: Product/flow filter not visible; row status is not an independently verified status for each year. | K13: https://www.dian.gov.co/dian/cifras/Paginas/EstadisticasComEx.aspx | L13: evidence/dian_fob.png | M13: evidence/dian_weight.png
A14: 8 | B14: 08 - Agosto | C14: -57.4 | D14: -202.81 | E14: 2.5331 | F14: -114.32 | G14: -230.35 | H14: 1.015 | I14: C | J14: Product/flow filter not visible; row status is not an independently verified status for each year. | K14: https://www.dian.gov.co/dian/cifras/Paginas/EstadisticasComEx.aspx | L14: evidence/dian_fob.png | M14: evidence/dian_weight.png
A15: 9 | B15: 09 - Septiembre | C15: -67.39 | D15: -338.57 | E15: 4.0244 | F15: -142.9 | G15: -320.91 | H15: 1.246 | I15: O | J15: Product/flow filter not visible; row status is not an independently verified status for each year. | K15: https://www.dian.gov.co/dian/cifras/Paginas/EstadisticasComEx.aspx | L15: evidence/dian_fob.png | M15: evidence/dian_weight.png
A16: 10 | B16: 10 - Octubre | C16: -28.43 | D16: -190.17 | E16: 5.6883 | F16: -61.35 | G16: -173.95 | H16: 1.835 | I16: O | J16: Product/flow filter not visible; row status is not an independently verified status for each year. October 2026 is incomplete as of 27 October; exact cutoff and prior-year matched cutoff unknown. | K16: https://www.dian.gov.co/dian/cifras/Paginas/EstadisticasComEx.aspx | L16: evidence/dian_fob.png | M16: evidence/dian_weight.png
B18: Visible-month sum | C18: =SUM(C7:C16) -> -676.77 | D18: =SUM(D7:D16) -> -1553.25 | F18: =SUM(F7:F16) -> -1223.45 | G18: =SUM(G7:G16) -> -2074.45
B20: Displayed total | C20: -710.14 | D20: -1553.25 | E20: 1.1872 | F20: -1293.11 | G20: -2074.45 | H20: 0.604 | I20: C y O | J20: Not a validated Jan-Oct aggregate: 2025 totals exceed visible rows. | K20: https://www.dian.gov.co/dian/cifras/Paginas/EstadisticasComEx.aspx
B22: Total minus visible sum | C22: =C20-C18 -> -33.37 | D22: =D20-D18 -> 0 | F22: =F20-F18 -> -69.66 | G22: =G20-G18 -> 0
A24: 2025 discrepancies are USD 33.37 million and 69.66 million kg in magnitude, too large to be display rounding. Do not invent missing months or adjust the data to force agreement.

Sheet Monthly comparison
A1: MONTHLY COMPARISON | CHART-READY
A2: Calculated from the ten visible rows, not from displayed totals. All values are absolute magnitudes. FOB/weight is a ratio, not a verified import price unless flow and product filters are confirmed.
A6: Month | B6: FOB 2025 (USD m) | C6: FOB 2026 (USD m) | D6: FOB YoY | E6: FOB increase (USD m) | F6: Weight 2025 (m kg) | G6: Weight 2026 (m kg) | H6: Weight YoY | I6: FOB/weight 2025 (USD/kg) | J6: FOB/weight 2026 (USD/kg) | K6: Ratio YoY | L6: Cum. FOB 2025 (USD m) | M6: Cum. FOB 2026 (USD m) | N6: Cum. FOB increase (USD m) | O6: Row status | P6: Coverage flag | Q6: Source URL
A7: Jan | B7: =ABS('DIAN raw'!C7) -> 78.16 | C7: =ABS('DIAN raw'!D7) -> 68.84 | D7: =IFERROR(C7/B7-1,"") -> -0.11924258 | E7: =C7-B7 -> -9.32 | F7: =ABS('DIAN raw'!F7) -> 120.15 | G7: =ABS('DIAN raw'!G7) -> 149.79 | H7: =IFERROR(G7/F7-1,"") -> 0.24669164 | I7: =IFERROR(B7/F7,"") -> 0.65052018 | J7: =IFERROR(C7/G7,"") -> 0.45957674 | K7: =IFERROR(J7/I7-1,"") -> -0.29352424 | L7: =SUM(B$7:B7) -> 78.16 | M7: =SUM(C$7:C7) -> 68.84 | N7: =M7-L7 -> -9.32 | O7: ='DIAN raw'!I7 -> C | P7: Filter unverified; C row | Q7: https://www.dian.gov.co/dian/cifras/Paginas/EstadisticasComEx.aspx
A8: Feb | B8: =ABS('DIAN raw'!C8) -> 61.47 | C8: =ABS('DIAN raw'!D8) -> 79.94 | D8: =IFERROR(C8/B8-1,"") -> 0.30047177 | E8: =C8-B8 -> 18.47 | F8: =ABS('DIAN raw'!F8) -> 86.44 | G8: =ABS('DIAN raw'!G8) -> 167.11 | H8: =IFERROR(G8/F8-1,"") -> 0.9332485 | I8: =IFERROR(B8/F8,"") -> 0.71112911 | J8: =IFERROR(C8/G8,"") -> 0.47836754 | K8: =IFERROR(J8/I8-1,"") -> -0.32731267 | L8: =SUM(B$7:B8) -> 139.63 | M8: =SUM(C$7:C8) -> 148.78 | N8: =M8-L8 -> 9.15 | O8: ='DIAN raw'!I8 -> C | P8: Filter unverified; C row | Q8: https://www.dian.gov.co/dian/cifras/Paginas/EstadisticasComEx.aspx
A9: Mar | B9: =ABS('DIAN raw'!C9) -> 64.28 | C9: =ABS('DIAN raw'!D9) -> 77.95 | D9: =IFERROR(C9/B9-1,"") -> 0.21266335 | E9: =C9-B9 -> 13.67 | F9: =ABS('DIAN raw'!F9) -> 97.89 | G9: =ABS('DIAN raw'!G9) -> 155.46 | H9: =IFERROR(G9/F9-1,"") -> 0.5881091 | I9: =IFERROR(B9/F9,"") -> 0.65665543 | J9: =IFERROR(C9/G9,"") -> 0.50141516 | K9: =IFERROR(J9/I9-1,"") -> -0.23641055 | L9: =SUM(B$7:B9) -> 203.91 | M9: =SUM(C$7:C9) -> 226.73 | N9: =M9-L9 -> 22.82 | O9: ='DIAN raw'!I9 -> C | P9: Filter unverified; C row | Q9: https://www.dian.gov.co/dian/cifras/Paginas/EstadisticasComEx.aspx
A10: Apr | B10: =ABS('DIAN raw'!C10) -> 108.5 | C10: =ABS('DIAN raw'!D10) -> 120.08 | D10: =IFERROR(C10/B10-1,"") -> 0.10672811 | E10: =C10-B10 -> 11.58 | F10: =ABS('DIAN raw'!F10) -> 203.86 | G10: =ABS('DIAN raw'!G10) -> 184.91 | H10: =IFERROR(G10/F10-1,"") -> -0.09295595 | I10: =IFERROR(B10/F10,"") -> 0.532228 | J10: =IFERROR(C10/G10,"") -> 0.649397 | K10: =IFERROR(J10/I10-1,"") -> 0.22014814 | L10: =SUM(B$7:B10) -> 312.41 | M10: =SUM(C$7:C10) -> 346.81 | N10: =M10-L10 -> 34.4 | O10: ='DIAN raw'!I10 -> C | P10: Filter unverified; C row | Q10: https://www.dian.gov.co/dian/cifras/Paginas/EstadisticasComEx.aspx
A11: May | B11: =ABS('DIAN raw'!C11) -> 55.22 | C11: =ABS('DIAN raw'!D11) -> 144.8 | D11: =IFERROR(C11/B11-1,"") -> 1.6222383 | E11: =C11-B11 -> 89.58 | F11: =ABS('DIAN raw'!F11) -> 105.23 | G11: =ABS('DIAN raw'!G11) -> 224.59 | H11: =IFERROR(G11/F11-1,"") -> 1.1342773 | I11: =IFERROR(B11/F11,"") -> 0.5247553 | J11: =IFERROR(C11/G11,"") -> 0.6447304 | K11: =IFERROR(J11/I11-1,"") -> 0.22863056 | L11: =SUM(B$7:B11) -> 367.63 | M11: =SUM(C$7:C11) -> 491.61 | N11: =M11-L11 -> 123.98 | O11: ='DIAN raw'!I11 -> C | P11: Filter unverified; C row | Q11: https://www.dian.gov.co/dian/cifras/Paginas/EstadisticasComEx.aspx
A12: Jun | B12: =ABS('DIAN raw'!C12) -> 64.75 | C12: =ABS('DIAN raw'!D12) -> 126.88 | D12: =IFERROR(C12/B12-1,"") -> 0.95953668 | E12: =C12-B12 -> 62.13 | F12: =ABS('DIAN raw'!F12) -> 118.74 | G12: =ABS('DIAN raw'!G12) -> 172.54 | H12: =IFERROR(G12/F12-1,"") -> 0.45309079 | I12: =IFERROR(B12/F12,"") -> 0.54530908 | J12: =IFERROR(C12/G12,"") -> 0.73536571 | K12: =IFERROR(J12/I12-1,"") -> 0.34853011 | L12: =SUM(B$7:B12) -> 432.38 | M12: =SUM(C$7:C12) -> 618.49 | N12: =M12-L12 -> 186.11 | O12: ='DIAN raw'!I12 -> C | P12: Filter unverified; C row | Q12: https://www.dian.gov.co/dian/cifras/Paginas/EstadisticasComEx.aspx
A13: Jul | B13: =ABS('DIAN raw'!C13) -> 91.17 | C13: =ABS('DIAN raw'!D13) -> 203.21 | D13: =IFERROR(C13/B13-1,"") -> 1.228913 | E13: =C13-B13 -> 112.04 | F13: =ABS('DIAN raw'!F13) -> 172.57 | G13: =ABS('DIAN raw'!G13) -> 294.84 | H13: =IFERROR(G13/F13-1,"") -> 0.70852408 | I13: =IFERROR(B13/F13,"") -> 0.52830735 | J13: =IFERROR(C13/G13,"") -> 0.68922127 | K13: =IFERROR(J13/I13-1,"") -> 0.30458391 | L13: =SUM(B$7:B13) -> 523.55 | M13: =SUM(C$7:C13) -> 821.7 | N13: =M13-L13 -> 298.15 | O13: ='DIAN raw'!I13 -> C | P13: Filter unverified; C row | Q13: https://www.dian.gov.co/dian/cifras/Paginas/EstadisticasComEx.aspx
A14: Aug | B14: =ABS('DIAN raw'!C14) -> 57.4 | C14: =ABS('DIAN raw'!D14) -> 202.81 | D14: =IFERROR(C14/B14-1,"") -> 2.5332753 | E14: =C14-B14 -> 145.41 | F14: =ABS('DIAN raw'!F14) -> 114.32 | G14: =ABS('DIAN raw'!G14) -> 230.35 | H14: =IFERROR(G14/F14-1,"") -> 1.014958 | I14: =IFERROR(B14/F14,"") -> 0.50209937 | J14: =IFERROR(C14/G14,"") -> 0.8804428 | K14: =IFERROR(J14/I14-1,"") -> 0.75352302 | L14: =SUM(B$7:B14) -> 580.95 | M14: =SUM(C$7:C14) -> 1024.51 | N14: =M14-L14 -> 443.56 | O14: ='DIAN raw'!I14 -> C | P14: Filter unverified; C row | Q14: https://www.dian.gov.co/dian/cifras/Paginas/EstadisticasComEx.aspx
A15: Sep | B15: =ABS('DIAN raw'!C15) -> 67.39 | C15: =ABS('DIAN raw'!D15) -> 338.57 | D15: =IFERROR(C15/B15-1,"") -> 4.0240392 | E15: =C15-B15 -> 271.18 | F15: =ABS('DIAN raw'!F15) -> 142.9 | G15: =ABS('DIAN raw'!G15) -> 320.91 | H15: =IFERROR(G15/F15-1,"") -> 1.2456963 | I15: =IFERROR(B15/F15,"") -> 0.47158852 | J15: =IFERROR(C15/G15,"") -> 1.055031 | K15: =IFERROR(J15/I15-1,"") -> 1.2371855 | L15: =SUM(B$7:B15) -> 648.34 | M15: =SUM(C$7:C15) -> 1363.08 | N15: =M15-L15 -> 714.74 | O15: ='DIAN raw'!I15 -> O | P15: Filter unverified; O row | Q15: https://www.dian.gov.co/dian/cifras/Paginas/EstadisticasComEx.aspx
A16: Oct | B16: =ABS('DIAN raw'!C16) -> 28.43 | C16: =ABS('DIAN raw'!D16) -> 190.17 | D16: =IFERROR(C16/B16-1,"") -> 5.6890609 | E16: =C16-B16 -> 161.74 | F16: =ABS('DIAN raw'!F16) -> 61.35 | G16: =ABS('DIAN raw'!G16) -> 173.95 | H16: =IFERROR(G16/F16-1,"") -> 1.8353708 | I16: =IFERROR(B16/F16,"") -> 0.46340668 | J16: =IFERROR(C16/G16,"") -> 1.0932452 | K16: =IFERROR(J16/I16-1,"") -> 1.3591485 | L16: =SUM(B$7:B16) -> 676.77 | M16: =SUM(C$7:C16) -> 1553.25 | N16: =M16-L16 -> 876.48 | O16: ='DIAN raw'!I16 -> O | P16: Filter unverified; O row; October partial/cutoff unknown | Q16: https://www.dian.gov.co/dian/cifras/Paginas/EstadisticasComEx.aspx
A19: No rolling-12-month series is calculated: November and December 2025 are not supplied. October 2026 is incomplete; do not annualize its displayed value.

Sheet Monthly long
A1: MONTHLY LONG | ONE ROW PER YEAR-MONTH
A2: 20 screenshot observations for graphing and database work. HS6/HS10 remain blank because product filters are cropped. Original signs are preserved alongside absolute magnitudes.
A6: Month | B6: Year | C6: Month no. | D6: FOB signed (USD m) | E6: Weight signed (m kg) | F6: FOB magnitude (USD m) | G6: Weight magnitude (m kg) | H6: FOB magnitude (USD) | I6: Weight magnitude (kg) | J6: FOB/weight (USD/kg) | K6: Row status shown | L6: Verified HS6 | M6: Verified HS10 | N6: Product context | O6: Flow context | P6: Snapshot date | Q6: Source URL | R6: Period / status note
A7: 45658 | B7: 2025 | C7: 1 | D7: ='DIAN raw'!C7 -> -78.16 | E7: ='DIAN raw'!F7 -> -120.15 | F7: =ABS(D7) -> 78.16 | G7: =ABS(E7) -> 120.15 | H7: =F7*Settings!$B$8 -> 78160000 | I7: =G7*Settings!$B$8 -> 120150000 | J7: =IFERROR(F7/G7,"") -> 0.65052018 | K7: ='DIAN raw'!I7 -> C | N7: User gas/LNG discussion; exact selection unverified | O7: Negative display; imports vs net balance unverified | P7: 2026-10-27 | Q7: https://www.dian.gov.co/dian/cifras/Paginas/EstadisticasComEx.aspx | R7: Shared comparison-row status; not independently assigned by year.
A8: 45689 | B8: 2025 | C8: 2 | D8: ='DIAN raw'!C8 -> -61.47 | E8: ='DIAN raw'!F8 -> -86.44 | F8: =ABS(D8) -> 61.47 | G8: =ABS(E8) -> 86.44 | H8: =F8*Settings!$B$8 -> 61470000 | I8: =G8*Settings!$B$8 -> 86440000 | J8: =IFERROR(F8/G8,"") -> 0.71112911 | K8: ='DIAN raw'!I8 -> C | N8: User gas/LNG discussion; exact selection unverified | O8: Negative display; imports vs net balance unverified | P8: 2026-10-27 | Q8: https://www.dian.gov.co/dian/cifras/Paginas/EstadisticasComEx.aspx | R8: Shared comparison-row status; not independently assigned by year.
A9: 45717 | B9: 2025 | C9: 3 | D9: ='DIAN raw'!C9 -> -64.28 | E9: ='DIAN raw'!F9 -> -97.89 | F9: =ABS(D9) -> 64.28 | G9: =ABS(E9) -> 97.89 | H9: =F9*Settings!$B$8 -> 64280000 | I9: =G9*Settings!$B$8 -> 97890000 | J9: =IFERROR(F9/G9,"") -> 0.65665543 | K9: ='DIAN raw'!I9 -> C | N9: User gas/LNG discussion; exact selection unverified | O9: Negative display; imports vs net balance unverified | P9: 2026-10-27 | Q9: https://www.dian.gov.co/dian/cifras/Paginas/EstadisticasComEx.aspx | R9: Shared comparison-row status; not independently assigned by year.
A10: 45748 | B10: 2025 | C10: 4 | D10: ='DIAN raw'!C10 -> -108.5 | E10: ='DIAN raw'!F10 -> -203.86 | F10: =ABS(D10) -> 108.5 | G10: =ABS(E10) -> 203.86 | H10: =F10*Settings!$B$8 -> 108500000 | I10: =G10*Settings!$B$8 -> 203860000 | J10: =IFERROR(F10/G10,"") -> 0.532228 | K10: ='DIAN raw'!I10 -> C | N10: User gas/LNG discussion; exact selection unverified | O10: Negative display; imports vs net balance unverified | P10: 2026-10-27 | Q10: https://www.dian.gov.co/dian/cifras/Paginas/EstadisticasComEx.aspx | R10: Shared comparison-row status; not independently assigned by year.
A11: 45778 | B11: 2025 | C11: 5 | D11: ='DIAN raw'!C11 -> -55.22 | E11: ='DIAN raw'!F11 -> -105.23 | F11: =ABS(D11) -> 55.22 | G11: =ABS(E11) -> 105.23 | H11: =F11*Settings!$B$8 -> 55220000 | I11: =G11*Settings!$B$8 -> 105230000 | J11: =IFERROR(F11/G11,"") -> 0.5247553 | K11: ='DIAN raw'!I11 -> C | N11: User gas/LNG discussion; exact selection unverified | O11: Negative display; imports vs net balance unverified | P11: 2026-10-27 | Q11: https://www.dian.gov.co/dian/cifras/Paginas/EstadisticasComEx.aspx | R11: Shared comparison-row status; not independently assigned by year.
A12: 45809 | B12: 2025 | C12: 6 | D12: ='DIAN raw'!C12 -> -64.75 | E12: ='DIAN raw'!F12 -> -118.74 | F12: =ABS(D12) -> 64.75 | G12: =ABS(E12) -> 118.74 | H12: =F12*Settings!$B$8 -> 64750000 | I12: =G12*Settings!$B$8 -> 118740000 | J12: =IFERROR(F12/G12,"") -> 0.54530908 | K12: ='DIAN raw'!I12 -> C | N12: User gas/LNG discussion; exact selection unverified | O12: Negative display; imports vs net balance unverified | P12: 2026-10-27 | Q12: https://www.dian.gov.co/dian/cifras/Paginas/EstadisticasComEx.aspx | R12: Shared comparison-row status; not independently assigned by year.
A13: 45839 | B13: 2025 | C13: 7 | D13: ='DIAN raw'!C13 -> -91.17 | E13: ='DIAN raw'!F13 -> -172.57 | F13: =ABS(D13) -> 91.17 | G13: =ABS(E13) -> 172.57 | H13: =F13*Settings!$B$8 -> 91170000 | I13: =G13*Settings!$B$8 -> 172570000 | J13: =IFERROR(F13/G13,"") -> 0.52830735 | K13: ='DIAN raw'!I13 -> C | N13: User gas/LNG discussion; exact selection unverified | O13: Negative display; imports vs net balance unverified | P13: 2026-10-27 | Q13: https://www.dian.gov.co/dian/cifras/Paginas/EstadisticasComEx.aspx | R13: Shared comparison-row status; not independently assigned by year.
A14: 45870 | B14: 2025 | C14: 8 | D14: ='DIAN raw'!C14 -> -57.4 | E14: ='DIAN raw'!F14 -> -114.32 | F14: =ABS(D14) -> 57.4 | G14: =ABS(E14) -> 114.32 | H14: =F14*Settings!$B$8 -> 57400000 | I14: =G14*Settings!$B$8 -> 114320000 | J14: =IFERROR(F14/G14,"") -> 0.50209937 | K14: ='DIAN raw'!I14 -> C | N14: User gas/LNG discussion; exact selection unverified | O14: Negative display; imports vs net balance unverified | P14: 2026-10-27 | Q14: https://www.dian.gov.co/dian/cifras/Paginas/EstadisticasComEx.aspx | R14: Shared comparison-row status; not independently assigned by year.
A15: 45901 | B15: 2025 | C15: 9 | D15: ='DIAN raw'!C15 -> -67.39 | E15: ='DIAN raw'!F15 -> -142.9 | F15: =ABS(D15) -> 67.39 | G15: =ABS(E15) -> 142.9 | H15: =F15*Settings!$B$8 -> 67390000 | I15: =G15*Settings!$B$8 -> 142900000 | J15: =IFERROR(F15/G15,"") -> 0.47158852 | K15: ='DIAN raw'!I15 -> O | N15: User gas/LNG discussion; exact selection unverified | O15: Negative display; imports vs net balance unverified | P15: 2026-10-27 | Q15: https://www.dian.gov.co/dian/cifras/Paginas/EstadisticasComEx.aspx | R15: Shared comparison-row status; not independently assigned by year.
A16: 45931 | B16: 2025 | C16: 10 | D16: ='DIAN raw'!C16 -> -28.43 | E16: ='DIAN raw'!F16 -> -61.35 | F16: =ABS(D16) -> 28.43 | G16: =ABS(E16) -> 61.35 | H16: =F16*Settings!$B$8 -> 28430000 | I16: =G16*Settings!$B$8 -> 61350000 | J16: =IFERROR(F16/G16,"") -> 0.46340668 | K16: ='DIAN raw'!I16 -> O | N16: User gas/LNG discussion; exact selection unverified | O16: Negative display; imports vs net balance unverified | P16: 2026-10-27 | Q16: https://www.dian.gov.co/dian/cifras/Paginas/EstadisticasComEx.aspx | R16: Shared comparison-row status; not independently assigned by year.
A17: 46023 | B17: 2026 | C17: 1 | D17: ='DIAN raw'!D7 -> -68.84 | E17: ='DIAN raw'!G7 -> -149.79 | F17: =ABS(D17) -> 68.84 | G17: =ABS(E17) -> 149.79 | H17: =F17*Settings!$B$8 -> 68840000 | I17: =G17*Settings!$B$8 -> 149790000 | J17: =IFERROR(F17/G17,"") -> 0.45957674 | K17: ='DIAN raw'!I7 -> C | N17: User gas/LNG discussion; exact selection unverified | O17: Negative display; imports vs net balance unverified | P17: 2026-10-27 | Q17: https://www.dian.gov.co/dian/cifras/Paginas/EstadisticasComEx.aspx | R17: Shared comparison-row status; not independently assigned by year.
A18: 46054 | B18: 2026 | C18: 2 | D18: ='DIAN raw'!D8 -> -79.94 | E18: ='DIAN raw'!G8 -> -167.11 | F18: =ABS(D18) -> 79.94 | G18: =ABS(E18) -> 167.11 | H18: =F18*Settings!$B$8 -> 79940000 | I18: =G18*Settings!$B$8 -> 167110000 | J18: =IFERROR(F18/G18,"") -> 0.47836754 | K18: ='DIAN raw'!I8 -> C | N18: User gas/LNG discussion; exact selection unverified | O18: Negative display; imports vs net balance unverified | P18: 2026-10-27 | Q18: https://www.dian.gov.co/dian/cifras/Paginas/EstadisticasComEx.aspx | R18: Shared comparison-row status; not independently assigned by year.
A19: 46082 | B19: 2026 | C19: 3 | D19: ='DIAN raw'!D9 -> -77.95 | E19: ='DIAN raw'!G9 -> -155.46 | F19: =ABS(D19) -> 77.95 | G19: =ABS(E19) -> 155.46 | H19: =F19*Settings!$B$8 -> 77950000 | I19: =G19*Settings!$B$8 -> 155460000 | J19: =IFERROR(F19/G19,"") -> 0.50141516 | K19: ='DIAN raw'!I9 -> C | N19: User gas/LNG discussion; exact selection unverified | O19: Negative display; imports vs net balance unverified | P19: 2026-10-27 | Q19: https://www.dian.gov.co/dian/cifras/Paginas/EstadisticasComEx.aspx | R19: Shared comparison-row status; not independently assigned by year.
A20: 46113 | B20: 2026 | C20: 4 | D20: ='DIAN raw'!D10 -> -120.08 | E20: ='DIAN raw'!G10 -> -184.91 | F20: =ABS(D20) -> 120.08 | G20: =ABS(E20) -> 184.91 | H20: =F20*Settings!$B$8 -> 120080000 | I20: =G20*Settings!$B$8 -> 184910000 | J20: =IFERROR(F20/G20,"") -> 0.649397 | K20: ='DIAN raw'!I10 -> C | N20: User gas/LNG discussion; exact selection unverified | O20: Negative display; imports vs net balance unverified | P20: 2026-10-27 | Q20: https://www.dian.gov.co/dian/cifras/Paginas/EstadisticasComEx.aspx | R20: Shared comparison-row status; not independently assigned by year.
A21: 46143 | B21: 2026 | C21: 5 | D21: ='DIAN raw'!D11 -> -144.8 | E21: ='DIAN raw'!G11 -> -224.59 | F21: =ABS(D21) -> 144.8 | G21: =ABS(E21) -> 224.59 | H21: =F21*Settings!$B$8 -> 144800000 | I21: =G21*Settings!$B$8 -> 224590000 | J21: =IFERROR(F21/G21,"") -> 0.6447304 | K21: ='DIAN raw'!I11 -> C | N21: User gas/LNG discussion; exact selection unverified | O21: Negative display; imports vs net balance unverified | P21: 2026-10-27 | Q21: https://www.dian.gov.co/dian/cifras/Paginas/EstadisticasComEx.aspx | R21: Shared comparison-row status; not independently assigned by year.
A22: 46174 | B22: 2026 | C22: 6 | D22: ='DIAN raw'!D12 -> -126.88 | E22: ='DIAN raw'!G12 -> -172.54 | F22: =ABS(D22) -> 126.88 | G22: =ABS(E22) -> 172.54 | H22: =F22*Settings!$B$8 -> 126880000 | I22: =G22*Settings!$B$8 -> 172540000 | J22: =IFERROR(F22/G22,"") -> 0.73536571 | K22: ='DIAN raw'!I12 -> C | N22: User gas/LNG discussion; exact selection unverified | O22: Negative display; imports vs net balance unverified | P22: 2026-10-27 | Q22: https://www.dian.gov.co/dian/cifras/Paginas/EstadisticasComEx.aspx | R22: Shared comparison-row status; not independently assigned by year.
A23: 46204 | B23: 2026 | C23: 7 | D23: ='DIAN raw'!D13 -> -203.21 | E23: ='DIAN raw'!G13 -> -294.84 | F23: =ABS(D23) -> 203.21 | G23: =ABS(E23) -> 294.84 | H23: =F23*Settings!$B$8 -> 203210000 | I23: =G23*Settings!$B$8 -> 294840000 | J23: =IFERROR(F23/G23,"") -> 0.68922127 | K23: ='DIAN raw'!I13 -> C | N23: User gas/LNG discussion; exact selection unverified | O23: Negative display; imports vs net balance unverified | P23: 2026-10-27 | Q23: https://www.dian.gov.co/dian/cifras/Paginas/EstadisticasComEx.aspx | R23: Shared comparison-row status; not independently assigned by year.
A24: 46235 | B24: 2026 | C24: 8 | D24: ='DIAN raw'!D14 -> -202.81 | E24: ='DIAN raw'!G14 -> -230.35 | F24: =ABS(D24) -> 202.81 | G24: =ABS(E24) -> 230.35 | H24: =F24*Settings!$B$8 -> 202810000 | I24: =G24*Settings!$B$8 -> 230350000 | J24: =IFERROR(F24/G24,"") -> 0.8804428 | K24: ='DIAN raw'!I14 -> C | N24: User gas/LNG discussion; exact selection unverified | O24: Negative display; imports vs net balance unverified | P24: 2026-10-27 | Q24: https://www.dian.gov.co/dian/cifras/Paginas/EstadisticasComEx.aspx | R24: Shared comparison-row status; not independently assigned by year.
A25: 46266 | B25: 2026 | C25: 9 | D25: ='DIAN raw'!D15 -> -338.57 | E25: ='DIAN raw'!G15 -> -320.91 | F25: =ABS(D25) -> 338.57 | G25: =ABS(E25) -> 320.91 | H25: =F25*Settings!$B$8 -> 338570000 | I25: =G25*Settings!$B$8 -> 320910000 | J25: =IFERROR(F25/G25,"") -> 1.055031 | K25: ='DIAN raw'!I15 -> O | N25: User gas/LNG discussion; exact selection unverified | O25: Negative display; imports vs net balance unverified | P25: 2026-10-27 | Q25: https://www.dian.gov.co/dian/cifras/Paginas/EstadisticasComEx.aspx | R25: Shared comparison-row status; not independently assigned by year.
A26: 46296 | B26: 2026 | C26: 10 | D26: ='DIAN raw'!D16 -> -190.17 | E26: ='DIAN raw'!G16 -> -173.95 | F26: =ABS(D26) -> 190.17 | G26: =ABS(E26) -> 173.95 | H26: =F26*Settings!$B$8 -> 190170000 | I26: =G26*Settings!$B$8 -> 173950000 | J26: =IFERROR(F26/G26,"") -> 1.0932452 | K26: ='DIAN raw'!I16 -> O | N26: User gas/LNG discussion; exact selection unverified | O26: Negative display; imports vs net balance unverified | P26: 2026-10-27 | Q26: https://www.dian.gov.co/dian/cifras/Paginas/EstadisticasComEx.aspx | R26: Shared comparison-row status; not independently assigned by year. Current-month partial; cutoff unknown.

Sheet Period analysis
A1: PERIOD ANALYSIS | MATCHED MONTHS
A2: January-August is the C-labelled core. Later periods include O-labelled rows and October is incomplete. Arithmetic decompositions are conditional on the series representing comparable gross imports.
A6: Period | B6: FOB 2025 (USD m) | C6: FOB 2026 (USD m) | D6: Increase (USD m) | E6: FOB YoY | F6: Weight 2025 (m kg) | G6: Weight 2026 (m kg) | H6: Weight YoY | I6: FOB/weight 2025 (USD/kg) | J6: FOB/weight 2026 (USD/kg) | K6: Ratio YoY | L6: Weight effect at 2025 ratio (USD m) | M6: Ratio effect at 2026 weight (USD m) | N6: Effect sum check | O6: Weight share of increase | P6: Coverage / interpretation
A7: Jan-Aug (C core) | B7: =SUM('Monthly comparison'!B7:B14) -> 580.95 | C7: =SUM('Monthly comparison'!C7:C14) -> 1024.51 | D7: =C7-B7 -> 443.56 | E7: =IFERROR(C7/B7-1,"") -> 0.76350805 | F7: =SUM('Monthly comparison'!F7:F14) -> 1019.2 | G7: =SUM('Monthly comparison'!G7:G14) -> 1579.59 | H7: =IFERROR(G7/F7-1,"") -> 0.5498332 | I7: =IFERROR(B7/F7,"") -> 0.57000589 | J7: =IFERROR(C7/G7,"") -> 0.64859236 | K7: =IFERROR(J7/I7-1,"") -> 0.13786957 | L7: =(G7-F7)*I7 -> 319.4256 | M7: =(J7-I7)*G7 -> 124.1344 | N7: =SUM(L7:M7)-D7 -> -1.1368684e-13 | O7: =IFERROR(L7/D7,"") -> 0.72014068 | P7: Eight C-labelled rows; main comparison.
A8: Jan-Jun (C) | B8: =SUM('Monthly comparison'!B7:B12) -> 432.38 | C8: =SUM('Monthly comparison'!C7:C12) -> 618.49 | D8: =C8-B8 -> 186.11 | E8: =IFERROR(C8/B8-1,"") -> 0.43043156 | F8: =SUM('Monthly comparison'!F7:F12) -> 732.31 | G8: =SUM('Monthly comparison'!G7:G12) -> 1054.4 | H8: =IFERROR(G8/F8-1,"") -> 0.4398274 | I8: =IFERROR(B8/F8,"") -> 0.59043301 | J8: =IFERROR(C8/G8,"") -> 0.58658005 | K8: =IFERROR(J8/I8-1,"") -> -0.0065256646 | L8: =(G8-F8)*I8 -> 190.17257 | M8: =(J8-I8)*G8 -> -4.0625693 | N8: =SUM(L8:M8)-D8 -> 5.6843419e-14 | O8: =IFERROR(L8/D8,"") -> 1.0218289 | P8: Six C-labelled rows.
A9: Jul-Aug (C) | B9: =SUM('Monthly comparison'!B13:B14) -> 148.57 | C9: =SUM('Monthly comparison'!C13:C14) -> 406.02 | D9: =C9-B9 -> 257.45 | E9: =IFERROR(C9/B9-1,"") -> 1.7328532 | F9: =SUM('Monthly comparison'!F13:F14) -> 286.89 | G9: =SUM('Monthly comparison'!G13:G14) -> 525.19 | H9: =IFERROR(G9/F9-1,"") -> 0.83063195 | I9: =IFERROR(B9/F9,"") -> 0.51786399 | J9: =IFERROR(C9/G9,"") -> 0.77309164 | K9: =IFERROR(J9/I9-1,"") -> 0.49284688 | L9: =(G9-F9)*I9 -> 123.40699 | M9: =(J9-I9)*G9 -> 134.04301 | N9: =SUM(L9:M9)-D9 -> 0 | O9: =IFERROR(L9/D9,"") -> 0.47934352 | P9: Two C-labelled rows; not a full quarter.
A10: Jan-Sep (C + O) | B10: =SUM('Monthly comparison'!B7:B15) -> 648.34 | C10: =SUM('Monthly comparison'!C7:C15) -> 1363.08 | D10: =C10-B10 -> 714.74 | E10: =IFERROR(C10/B10-1,"") -> 1.1024154 | F10: =SUM('Monthly comparison'!F7:F15) -> 1162.1 | G10: =SUM('Monthly comparison'!G7:G15) -> 1900.5 | H10: =IFERROR(G10/F10-1,"") -> 0.63540143 | I10: =IFERROR(B10/F10,"") -> 0.55790379 | J10: =IFERROR(C10/G10,"") -> 0.71722178 | K10: =IFERROR(J10/I10-1,"") -> 0.28556534 | L10: =(G10-F10)*I10 -> 411.95616 | M10: =(J10-I10)*G10 -> 302.78384 | N10: =SUM(L10:M10)-D10 -> 0 | O10: =IFERROR(L10/D10,"") -> 0.57637205 | P10: September is observed; may be revised.
A11: Jan-Oct visible rows | B11: =SUM('Monthly comparison'!B7:B16) -> 676.77 | C11: =SUM('Monthly comparison'!C7:C16) -> 1553.25 | D11: =C11-B11 -> 876.48 | E11: =IFERROR(C11/B11-1,"") -> 1.2950929 | F11: =SUM('Monthly comparison'!F7:F16) -> 1223.45 | G11: =SUM('Monthly comparison'!G7:G16) -> 2074.45 | H11: =IFERROR(G11/F11-1,"") -> 0.69557399 | I11: =IFERROR(B11/F11,"") -> 0.55316523 | J11: =IFERROR(C11/G11,"") -> 0.74875268 | K11: =IFERROR(J11/I11-1,"") -> 0.35357872 | L11: =(G11-F11)*I11 -> 470.74361 | M11: =(J11-I11)*G11 -> 405.73639 | N11: =SUM(L11:M11)-D11 -> -1.1368684e-13 | O11: =IFERROR(L11/D11,"") -> 0.53708426 | P11: October incomplete; 2025 displayed total does not reconcile.
A12: Displayed totals | B12: =ABS('DIAN raw'!C20) -> 710.14 | C12: =ABS('DIAN raw'!D20) -> 1553.25 | D12: =C12-B12 -> 843.11 | E12: =IFERROR(C12/B12-1,"") -> 1.1872448 | F12: =ABS('DIAN raw'!F20) -> 1293.11 | G12: =ABS('DIAN raw'!G20) -> 2074.45 | H12: =IFERROR(G12/F12-1,"") -> 0.60423321 | I12: =IFERROR(B12/F12,"") -> 0.54917215 | J12: =IFERROR(C12/G12,"") -> 0.74875268 | K12: =IFERROR(J12/I12-1,"") -> 0.36342071 | L12: =(G12-F12)*I12 -> 429.09017 | M12: =(J12-I12)*G12 -> 414.01983 | N12: =SUM(L12:M12)-D12 -> -1.1368684e-13 | O12: =IFERROR(L12/D12,"") -> 0.50893735 | P12: Not matched-month validated; 2025 totals disagree with visible rows.
A15: Exact decomposition: increase = (weight26 - weight25) x ratio25 + (ratio26 - ratio25) x weight26. The interaction term is allocated to the ratio effect. This is accounting, not proof of causality.
A17: The ratio can reflect contracts, product mix and timing. It is not a spot LNG price or a landed cost. If the series is net exports rather than imports, it is not a valid gross-import unit price.
A20: MACRO SCALE | JANUARY-AUGUST, FOB
A21: National goods deficit 2025 (USD m) | F21: 10604.5
A22: National goods deficit 2026 (USD m) | F22: 13877.1
A23: National deficit widening (USD m) | F23: =F22-F21 -> 3272.6
A24: Selected series FOB magnitude increase (USD m) | F24: =D7 -> 443.56
A25: Increase / national deficit widening | F25: =F24/F23 -> 0.13553749
A27: Conditional scale comparison, not a fully reconciled contribution: tariff/flow selection is not visible, exports may matter, and publication vintages can differ. DANE bulletin, 21 Oct 2026, p.13.
A29: https://www.dane.gov.co/files/operaciones/IMP/bol-IMP-ago2026.pdf

Sheet Monthly checks
A1: MONTHLY VALIDATION | DO NOT FORCE TOTALS
A2: Raw screenshot totals are separately stored. Monthly percent differences are tested against display rounding; large aggregate gaps are flagged, not silently corrected.
A6: Check | B6: Unit | C6: Visible-row sum / calculated | D6: Displayed total / benchmark | E6: Difference | F6: Tolerance | G6: Result | H6: Interpretation
A7: 2025 FOB reconciliation | B7: USD m | C7: =ABS('DIAN raw'!C18) -> 676.77 | D7: =ABS('DIAN raw'!C20) -> 710.14 | E7: =D7-C7 -> 33.37 | F7: 0.055 | G7: =IF(ABS(E7)<=F7,"PASS","REVIEW") -> REVIEW | H7: Tolerance = ten monthly rounding bounds plus one total rounding bound.
A8: 2026 FOB reconciliation | B8: USD m | C8: =ABS('DIAN raw'!D18) -> 1553.25 | D8: =ABS('DIAN raw'!D20) -> 1553.25 | E8: =D8-C8 -> 0 | F8: 0.055 | G8: =IF(ABS(E8)<=F8,"PASS","REVIEW") -> PASS | H8: Tolerance = ten monthly rounding bounds plus one total rounding bound.
A9: 2025 weight reconciliation | B9: million kg | C9: =ABS('DIAN raw'!F18) -> 1223.45 | D9: =ABS('DIAN raw'!F20) -> 1293.11 | E9: =D9-C9 -> 69.66 | F9: 0.055 | G9: =IF(ABS(E9)<=F9,"PASS","REVIEW") -> REVIEW | H9: Tolerance = ten monthly rounding bounds plus one total rounding bound.
A10: 2026 weight reconciliation | B10: million kg | C10: =ABS('DIAN raw'!G18) -> 2074.45 | D10: =ABS('DIAN raw'!G20) -> 2074.45 | E10: =D10-C10 -> 0 | F10: 0.055 | G10: =IF(ABS(E10)<=F10,"PASS","REVIEW") -> PASS | H10: Tolerance = ten monthly rounding bounds plus one total rounding bound.
A13: Jan FOB percentage | B13: fraction | C13: ='Monthly comparison'!D7 -> -0.11924258 | D13: ='DIAN raw'!E7 -> -0.1192 | E13: =C13-D13 -> -4.2579324e-05 | F13: 0.001 | G13: =IF(ABS(E13)<=F13,"PASS","REVIEW") -> PASS | H13: 0.1 percentage-point tolerance for values displayed to USD 0.01 million.
A14: Feb FOB percentage | B14: fraction | C14: ='Monthly comparison'!D8 -> 0.30047177 | D14: ='DIAN raw'!E8 -> 0.3004 | E14: =C14-D14 -> 7.177485e-05 | F14: 0.001 | G14: =IF(ABS(E14)<=F14,"PASS","REVIEW") -> PASS | H14: 0.1 percentage-point tolerance for values displayed to USD 0.01 million.
A15: Mar FOB percentage | B15: fraction | C15: ='Monthly comparison'!D9 -> 0.21266335 | D15: ='DIAN raw'!E9 -> 0.2127 | E15: =C15-D15 -> -3.6652147e-05 | F15: 0.001 | G15: =IF(ABS(E15)<=F15,"PASS","REVIEW") -> PASS | H15: 0.1 percentage-point tolerance for values displayed to USD 0.01 million.
A16: Apr FOB percentage | B16: fraction | C16: ='Monthly comparison'!D10 -> 0.10672811 | D16: ='DIAN raw'!E10 -> 0.1067 | E16: =C16-D16 -> 2.8110599e-05 | F16: 0.001 | G16: =IF(ABS(E16)<=F16,"PASS","REVIEW") -> PASS | H16: 0.1 percentage-point tolerance for values displayed to USD 0.01 million.
A17: May FOB percentage | B17: fraction | C17: ='Monthly comparison'!D11 -> 1.6222383 | D17: ='DIAN raw'!E11 -> 1.6221 | E17: =C17-D17 -> 0.00013831945 | F17: 0.001 | G17: =IF(ABS(E17)<=F17,"PASS","REVIEW") -> PASS | H17: 0.1 percentage-point tolerance for values displayed to USD 0.01 million.
A18: Jun FOB percentage | B18: fraction | C18: ='Monthly comparison'!D12 -> 0.95953668 | D18: ='DIAN raw'!E12 -> 0.9595 | E18: =C18-D18 -> 3.6679537e-05 | F18: 0.001 | G18: =IF(ABS(E18)<=F18,"PASS","REVIEW") -> PASS | H18: 0.1 percentage-point tolerance for values displayed to USD 0.01 million.
A19: Jul FOB percentage | B19: fraction | C19: ='Monthly comparison'!D13 -> 1.228913 | D19: ='DIAN raw'!E13 -> 1.229 | E19: =C19-D19 -> -8.6980366e-05 | F19: 0.001 | G19: =IF(ABS(E19)<=F19,"PASS","REVIEW") -> PASS | H19: 0.1 percentage-point tolerance for values displayed to USD 0.01 million.
A20: Aug FOB percentage | B20: fraction | C20: ='Monthly comparison'!D14 -> 2.5332753 | D20: ='DIAN raw'!E14 -> 2.5331 | E20: =C20-D20 -> 0.00017526132 | F20: 0.001 | G20: =IF(ABS(E20)<=F20,"PASS","REVIEW") -> PASS | H20: 0.1 percentage-point tolerance for values displayed to USD 0.01 million.
A21: Sep FOB percentage | B21: fraction | C21: ='Monthly comparison'!D15 -> 4.0240392 | D21: ='DIAN raw'!E15 -> 4.0244 | E21: =C21-D21 -> -0.00036082505 | F21: 0.001 | G21: =IF(ABS(E21)<=F21,"PASS","REVIEW") -> PASS | H21: 0.1 percentage-point tolerance for values displayed to USD 0.01 million.
A22: Oct FOB percentage | B22: fraction | C22: ='Monthly comparison'!D16 -> 5.6890609 | D22: ='DIAN raw'!E16 -> 5.6883 | E22: =C22-D22 -> 0.00076085121 | F22: 0.001 | G22: =IF(ABS(E22)<=F22,"PASS","REVIEW") -> PASS | H22: 0.1 percentage-point tolerance for values displayed to USD 0.01 million.
A25: Jan weight percentage | B25: fraction | C25: ='Monthly comparison'!H7 -> 0.24669164 | D25: ='DIAN raw'!H7 -> 0.247 | E25: =C25-D25 -> -0.00030836454 | F25: 0.001 | G25: =IF(ABS(E25)<=F25,"PASS","REVIEW") -> PASS | H25: 0.1 percentage-point tolerance for rounded published weights and growth.
A26: Feb weight percentage | B26: fraction | C26: ='Monthly comparison'!H8 -> 0.9332485 | D26: ='DIAN raw'!H8 -> 0.933 | E26: =C26-D26 -> 0.00024849607 | F26: 0.001 | G26: =IF(ABS(E26)<=F26,"PASS","REVIEW") -> PASS | H26: 0.1 percentage-point tolerance for rounded published weights and growth.
A27: Mar weight percentage | B27: fraction | C27: ='Monthly comparison'!H9 -> 0.5881091 | D27: ='DIAN raw'!H9 -> 0.588 | E27: =C27-D27 -> 0.00010910205 | F27: 0.001 | G27: =IF(ABS(E27)<=F27,"PASS","REVIEW") -> PASS | H27: 0.1 percentage-point tolerance for rounded published weights and growth.
A28: Apr weight percentage | B28: fraction | C28: ='Monthly comparison'!H10 -> -0.09295595 | D28: ='DIAN raw'!H10 -> -0.093 | E28: =C28-D28 -> 4.4049838e-05 | F28: 0.001 | G28: =IF(ABS(E28)<=F28,"PASS","REVIEW") -> PASS | H28: 0.1 percentage-point tolerance for rounded published weights and growth.
A29: May weight percentage | B29: fraction | C29: ='Monthly comparison'!H11 -> 1.1342773 | D29: ='DIAN raw'!H11 -> 1.134 | E29: =C29-D29 -> 0.00027729735 | F29: 0.001 | G29: =IF(ABS(E29)<=F29,"PASS","REVIEW") -> PASS | H29: 0.1 percentage-point tolerance for rounded published weights and growth.
A30: Jun weight percentage | B30: fraction | C30: ='Monthly comparison'!H12 -> 0.45309079 | D30: ='DIAN raw'!H12 -> 0.453 | E30: =C30-D30 -> 9.0786593e-05 | F30: 0.001 | G30: =IF(ABS(E30)<=F30,"PASS","REVIEW") -> PASS | H30: 0.1 percentage-point tolerance for rounded published weights and growth.
A31: Jul weight percentage | B31: fraction | C31: ='Monthly comparison'!H13 -> 0.70852408 | D31: ='DIAN raw'!H13 -> 0.708 | E31: =C31-D31 -> 0.00052407719 | F31: 0.001 | G31: =IF(ABS(E31)<=F31,"PASS","REVIEW") -> PASS | H31: 0.1 percentage-point tolerance for rounded published weights and growth.
A32: Aug weight percentage | B32: fraction | C32: ='Monthly comparison'!H14 -> 1.014958 | D32: ='DIAN raw'!H14 -> 1.015 | E32: =C32-D32 -> -4.1987404e-05 | F32: 0.001 | G32: =IF(ABS(E32)<=F32,"PASS","REVIEW") -> PASS | H32: 0.1 percentage-point tolerance for rounded published weights and growth.
A33: Sep weight percentage | B33: fraction | C33: ='Monthly comparison'!H15 -> 1.2456963 | D33: ='DIAN raw'!H15 -> 1.246 | E33: =C33-D33 -> -0.00030370889 | F33: 0.001 | G33: =IF(ABS(E33)<=F33,"PASS","REVIEW") -> PASS | H33: 0.1 percentage-point tolerance for rounded published weights and growth.
A34: Oct weight percentage | B34: fraction | C34: ='Monthly comparison'!H16 -> 1.8353708 | D34: ='DIAN raw'!H16 -> 1.835 | E34: =C34-D34 -> 0.00037082315 | F34: 0.001 | G34: =IF(ABS(E34)<=F34,"PASS","REVIEW") -> PASS | H34: 0.1 percentage-point tolerance for rounded published weights and growth.
A37: Unresolved metadata: product HS code; all-partner/national coverage; imports versus net trade; exact snapshot cutoff; reason for the non-reconciling 2025 totals. Signed data remain intact.

Sheet DIAN evidence
A1: EVIDENCE | USER-SUPPLIED SCREENSHOTS
A2: Original cropped tables. The underlying filter selections, dashboard page title and precise refresh/cutoff date are not visible.
A39: Image 1: FOB values. Image 2: net weights. Visual transcription; no OCR. Data snapshot labelled 2025/2026; captured during this conversation on 27 October 2026.
A41: https://www.dian.gov.co/dian/cifras/Paginas/EstadisticasComEx.aspx

Sheet Charts
A1: CHARTS | VERIFIED SERIES
A2: Editable Excel charts. Annual customs values are CIF. BMC lines are a forward supply-demand scenario, not imports.
A5: National customs series: only full calendar years are compared. Missing reported quantities are not filled.
A25: Partner chart: the 2025 WITS label Tanzania is reconciled to Trinidad and Tobago using DANE. The unaltered source label is retained in Partners.
A45: Forward scenario, not actual imports. Exact values come from the 14 rows visible in the supplied screenshot; no terminal-level bar values were inferred.
A66: Year | B66: United States | C66: Trinidad and Tobago | D66: United Kingdom | E66: Other reported partners
A67: 2017 | B67: =SUMIFS(Partners!$F$7:$F$43,Partners!$A$7:$A$43,A67,Partners!$B$7:$B$43,"271111",Partners!$D$7:$D$43,B$66)/Settings!$B$8 -> 0 | C67: =SUMIFS(Partners!$F$7:$F$43,Partners!$A$7:$A$43,A67,Partners!$B$7:$B$43,"271111",Partners!$D$7:$D$43,C$66)/Settings!$B$8 -> 0 | D67: =SUMIFS(Partners!$F$7:$F$43,Partners!$A$7:$A$43,A67,Partners!$B$7:$B$43,"271111",Partners!$D$7:$D$43,D$66)/Settings!$B$8 -> 0 | E67: =SUMIFS(Partners!$F$7:$F$43,Partners!$A$7:$A$43,A67,Partners!$B$7:$B$43,"271111")/Settings!$B$8-SUM(B67:D67) -> 11.92593
A68: 2018 | B68: =SUMIFS(Partners!$F$7:$F$43,Partners!$A$7:$A$43,A68,Partners!$B$7:$B$43,"271111",Partners!$D$7:$D$43,B$66)/Settings!$B$8 -> 39.55393 | C68: =SUMIFS(Partners!$F$7:$F$43,Partners!$A$7:$A$43,A68,Partners!$B$7:$B$43,"271111",Partners!$D$7:$D$43,C$66)/Settings!$B$8 -> 36.71102 | D68: =SUMIFS(Partners!$F$7:$F$43,Partners!$A$7:$A$43,A68,Partners!$B$7:$B$43,"271111",Partners!$D$7:$D$43,D$66)/Settings!$B$8 -> 32.60278 | E68: =SUMIFS(Partners!$F$7:$F$43,Partners!$A$7:$A$43,A68,Partners!$B$7:$B$43,"271111")/Settings!$B$8-SUM(B68:D68) -> 14.87964
A69: 2019 | B69: =SUMIFS(Partners!$F$7:$F$43,Partners!$A$7:$A$43,A69,Partners!$B$7:$B$43,"271111",Partners!$D$7:$D$43,B$66)/Settings!$B$8 -> 21.90239 | C69: =SUMIFS(Partners!$F$7:$F$43,Partners!$A$7:$A$43,A69,Partners!$B$7:$B$43,"271111",Partners!$D$7:$D$43,C$66)/Settings!$B$8 -> 7.83293 | D69: =SUMIFS(Partners!$F$7:$F$43,Partners!$A$7:$A$43,A69,Partners!$B$7:$B$43,"271111",Partners!$D$7:$D$43,D$66)/Settings!$B$8 -> 0 | E69: =SUMIFS(Partners!$F$7:$F$43,Partners!$A$7:$A$43,A69,Partners!$B$7:$B$43,"271111")/Settings!$B$8-SUM(B69:D69) -> 27.30873
A70: 2020 | B70: =SUMIFS(Partners!$F$7:$F$43,Partners!$A$7:$A$43,A70,Partners!$B$7:$B$43,"271111",Partners!$D$7:$D$43,B$66)/Settings!$B$8 -> 2.97281 | C70: =SUMIFS(Partners!$F$7:$F$43,Partners!$A$7:$A$43,A70,Partners!$B$7:$B$43,"271111",Partners!$D$7:$D$43,C$66)/Settings!$B$8 -> 13.41035 | D70: =SUMIFS(Partners!$F$7:$F$43,Partners!$A$7:$A$43,A70,Partners!$B$7:$B$43,"271111",Partners!$D$7:$D$43,D$66)/Settings!$B$8 -> 20.3398 | E70: =SUMIFS(Partners!$F$7:$F$43,Partners!$A$7:$A$43,A70,Partners!$B$7:$B$43,"271111")/Settings!$B$8-SUM(B70:D70) -> 23.18736
A71: 2021 | B71: =SUMIFS(Partners!$F$7:$F$43,Partners!$A$7:$A$43,A71,Partners!$B$7:$B$43,"271111",Partners!$D$7:$D$43,B$66)/Settings!$B$8 -> 14.51052 | C71: =SUMIFS(Partners!$F$7:$F$43,Partners!$A$7:$A$43,A71,Partners!$B$7:$B$43,"271111",Partners!$D$7:$D$43,C$66)/Settings!$B$8 -> 0 | D71: =SUMIFS(Partners!$F$7:$F$43,Partners!$A$7:$A$43,A71,Partners!$B$7:$B$43,"271111",Partners!$D$7:$D$43,D$66)/Settings!$B$8 -> 13.42246 | E71: =SUMIFS(Partners!$F$7:$F$43,Partners!$A$7:$A$43,A71,Partners!$B$7:$B$43,"271111")/Settings!$B$8-SUM(B71:D71) -> 0.00851
A72: 2022 | B72: =SUMIFS(Partners!$F$7:$F$43,Partners!$A$7:$A$43,A72,Partners!$B$7:$B$43,"271111",Partners!$D$7:$D$43,B$66)/Settings!$B$8 -> 87.55064 | C72: =SUMIFS(Partners!$F$7:$F$43,Partners!$A$7:$A$43,A72,Partners!$B$7:$B$43,"271111",Partners!$D$7:$D$43,C$66)/Settings!$B$8 -> 0 | D72: =SUMIFS(Partners!$F$7:$F$43,Partners!$A$7:$A$43,A72,Partners!$B$7:$B$43,"271111",Partners!$D$7:$D$43,D$66)/Settings!$B$8 -> 0 | E72: =SUMIFS(Partners!$F$7:$F$43,Partners!$A$7:$A$43,A72,Partners!$B$7:$B$43,"271111")/Settings!$B$8-SUM(B72:D72) -> 0
A73: 2023 | B73: =SUMIFS(Partners!$F$7:$F$43,Partners!$A$7:$A$43,A73,Partners!$B$7:$B$43,"271111",Partners!$D$7:$D$43,B$66)/Settings!$B$8 -> 410.85209 | C73: =SUMIFS(Partners!$F$7:$F$43,Partners!$A$7:$A$43,A73,Partners!$B$7:$B$43,"271111",Partners!$D$7:$D$43,C$66)/Settings!$B$8 -> 30.60301 | D73: =SUMIFS(Partners!$F$7:$F$43,Partners!$A$7:$A$43,A73,Partners!$B$7:$B$43,"271111",Partners!$D$7:$D$43,D$66)/Settings!$B$8 -> 0.00087 | E73: =SUMIFS(Partners!$F$7:$F$43,Partners!$A$7:$A$43,A73,Partners!$B$7:$B$43,"271111")/Settings!$B$8-SUM(B73:D73) -> 0
A74: 2024 | B74: =SUMIFS(Partners!$F$7:$F$43,Partners!$A$7:$A$43,A74,Partners!$B$7:$B$43,"271111",Partners!$D$7:$D$43,B$66)/Settings!$B$8 -> 771.97825 | C74: =SUMIFS(Partners!$F$7:$F$43,Partners!$A$7:$A$43,A74,Partners!$B$7:$B$43,"271111",Partners!$D$7:$D$43,C$66)/Settings!$B$8 -> 134.54294 | D74: =SUMIFS(Partners!$F$7:$F$43,Partners!$A$7:$A$43,A74,Partners!$B$7:$B$43,"271111",Partners!$D$7:$D$43,D$66)/Settings!$B$8 -> 38.92535 | E74: =SUMIFS(Partners!$F$7:$F$43,Partners!$A$7:$A$43,A74,Partners!$B$7:$B$43,"271111")/Settings!$B$8-SUM(B74:D74) -> 1.1368684e-13
A75: 2025 | B75: =SUMIFS(Partners!$F$7:$F$43,Partners!$A$7:$A$43,A75,Partners!$B$7:$B$43,"271111",Partners!$D$7:$D$43,B$66)/Settings!$B$8 -> 388.39081 | C75: =SUMIFS(Partners!$F$7:$F$43,Partners!$A$7:$A$43,A75,Partners!$B$7:$B$43,"271111",Partners!$D$7:$D$43,C$66)/Settings!$B$8 -> 390.80822 | D75: =SUMIFS(Partners!$F$7:$F$43,Partners!$A$7:$A$43,A75,Partners!$B$7:$B$43,"271111",Partners!$D$7:$D$43,D$66)/Settings!$B$8 -> 0.00463 | E75: =SUMIFS(Partners!$F$7:$F$43,Partners!$A$7:$A$43,A75,Partners!$B$7:$B$43,"271111")/Settings!$B$8-SUM(B75:D75) -> 0

Sheet Annual imports
A1: ANNUAL IMPORTS | CHART-READY
A2: LNG: 2017-2025. Gaseous natural gas: 2021-2025 only. Blank values mean unavailable in this extraction, not zero. World totals are not added to partner rows.
A6: Year | B6: LNG CIF (US$) | C6: Gaseous gas CIF (US$) | D6: Total natural gas CIF (US$) | E6: LNG CIF (US$ million) | F6: LNG reported quantity (tonnes) | G6: LNG CIF unit value (US$/tonne) | H6: LNG value YoY (%) | I6: Quantity status | J6: LNG source URL | K6: Gaseous-gas source URL
A7: 2017 | B7: ='Annual raw'!F7 -> 11925930 | D7: =IF(COUNT(B7:C7)=2,SUM(B7:C7),"") | E7: =B7/Settings!$B$8 -> 11.92593 | F7: =IF(ISNUMBER('Annual raw'!E7),'Annual raw'!E7/Settings!$B$9,"") -> 38942.6 | G7: =IF(AND(ISNUMBER(F7),F7>0),B7/F7,"") -> 306.2438 | I7: Reported | J7: https://wits.worldbank.org/trade/comtrade/en/country/COL/year/2017/tradeflow/Imports/partner/ALL/product/271111
A8: 2018 | B8: ='Annual raw'!F8 -> 123747360 | D8: =IF(COUNT(B8:C8)=2,SUM(B8:C8),"") | E8: =B8/Settings!$B$8 -> 123.74736 | F8: =IF(ISNUMBER('Annual raw'!E8),'Annual raw'!E8/Settings!$B$9,"") -> 239638 | G8: =IF(AND(ISNUMBER(F8),F8>0),B8/F8,"") -> 516.39289 | H8: =IFERROR(B8/B7-1,"") -> 9.3763279 | I8: Reported | J8: https://wits.worldbank.org/trade/comtrade/en/country/COL/year/2018/tradeflow/Imports/partner/ALL/product/271111
A9: 2019 | B9: ='Annual raw'!F9 -> 57044060 | D9: =IF(COUNT(B9:C9)=2,SUM(B9:C9),"") | E9: =B9/Settings!$B$8 -> 57.04406 | F9: =IF(ISNUMBER('Annual raw'!E9),'Annual raw'!E9/Settings!$B$9,"") | G9: =IF(AND(ISNUMBER(F9),F9>0),B9/F9,"") | H9: =IFERROR(B9/B8-1,"") -> -0.53902806 | I9: Missing in WITS; not zero | J9: https://wits.worldbank.org/trade/comtrade/en/country/COL/year/2019/tradeflow/Imports/partner/ALL/product/271111
A10: 2020 | B10: ='Annual raw'!F10 -> 59910330 | D10: =IF(COUNT(B10:C10)=2,SUM(B10:C10),"") | E10: =B10/Settings!$B$8 -> 59.91033 | F10: =IF(ISNUMBER('Annual raw'!E10),'Annual raw'!E10/Settings!$B$9,"") -> 296302 | G10: =IF(AND(ISNUMBER(F10),F10>0),B10/F10,"") -> 202.19347 | H10: =IFERROR(B10/B9-1,"") -> 0.050246599 | I10: Reported | J10: https://wits.worldbank.org/trade/comtrade/en/country/COL/year/2020/tradeflow/Imports/partner/ALL/product/271111
A11: 2021 | B11: ='Annual raw'!F11 -> 27941490 | C11: ='Annual raw'!F12 -> 43160 | D11: =IF(COUNT(B11:C11)=2,SUM(B11:C11),"") -> 27984650 | E11: =B11/Settings!$B$8 -> 27.94149 | F11: =IF(ISNUMBER('Annual raw'!E11),'Annual raw'!E11/Settings!$B$9,"") -> 44406 | G11: =IF(AND(ISNUMBER(F11),F11>0),B11/F11,"") -> 629.22781 | H11: =IFERROR(B11/B10-1,"") -> -0.53361148 | I11: Reported | J11: https://wits.worldbank.org/trade/comtrade/en/country/COL/year/2021/tradeflow/Imports/partner/ALL/product/271111 | K11: https://wits.worldbank.org/trade/comtrade/en/country/COL/year/2021/tradeflow/Imports/partner/ALL/product/271121
A12: 2022 | B12: ='Annual raw'!F13 -> 87550640 | C12: ='Annual raw'!F14 -> 84120 | D12: =IF(COUNT(B12:C12)=2,SUM(B12:C12),"") -> 87634760 | E12: =B12/Settings!$B$8 -> 87.55064 | F12: =IF(ISNUMBER('Annual raw'!E13),'Annual raw'!E13/Settings!$B$9,"") -> 60181 | G12: =IF(AND(ISNUMBER(F12),F12>0),B12/F12,"") -> 1454.7887 | H12: =IFERROR(B12/B11-1,"") -> 2.1333562 | I12: Reported | J12: https://wits.worldbank.org/trade/comtrade/en/country/COL/year/2022/tradeflow/Imports/partner/ALL/product/271111 | K12: https://wits.worldbank.org/trade/comtrade/en/country/COL/year/2022/tradeflow/Imports/partner/ALL/product/271121
A13: 2023 | B13: ='Annual raw'!F15 -> 441455970 | C13: ='Annual raw'!F16 -> 4930 | D13: =IF(COUNT(B13:C13)=2,SUM(B13:C13),"") -> 441460900 | E13: =B13/Settings!$B$8 -> 441.45597 | F13: =IF(ISNUMBER('Annual raw'!E15),'Annual raw'!E15/Settings!$B$9,"") | G13: =IF(AND(ISNUMBER(F13),F13>0),B13/F13,"") | H13: =IFERROR(B13/B12-1,"") -> 4.0422929 | I13: Missing in WITS; not zero | J13: https://wits.worldbank.org/trade/comtrade/en/country/COL/year/2023/tradeflow/Imports/partner/ALL/product/271111 | K13: https://wits.worldbank.org/trade/comtrade/en/country/COL/year/2023/tradeflow/Imports/partner/ALL/product/271121
A14: 2024 | B14: ='Annual raw'!F17 -> 945446540 | C14: ='Annual raw'!F18 -> 31740 | D14: =IF(COUNT(B14:C14)=2,SUM(B14:C14),"") -> 945478280 | E14: =B14/Settings!$B$8 -> 945.44654 | F14: =IF(ISNUMBER('Annual raw'!E17),'Annual raw'!E17/Settings!$B$9,"") -> 1625300 | G14: =IF(AND(ISNUMBER(F14),F14>0),B14/F14,"") -> 581.70586 | H14: =IFERROR(B14/B13-1,"") -> 1.1416554 | I14: Reported | J14: https://wits.worldbank.org/trade/comtrade/en/country/COL/year/2024/tradeflow/Imports/partner/ALL/product/271111 | K14: https://wits.worldbank.org/trade/comtrade/en/country/COL/year/2024/tradeflow/Imports/partner/ALL/product/271121
A15: 2025 | B15: ='Annual raw'!F19 -> 779203660 | C15: ='Annual raw'!F20 -> 27570 | D15: =IF(COUNT(B15:C15)=2,SUM(B15:C15),"") -> 779231230 | E15: =B15/Settings!$B$8 -> 779.20366 | F15: =IF(ISNUMBER('Annual raw'!E19),'Annual raw'!E19/Settings!$B$9,"") | G15: =IF(AND(ISNUMBER(F15),F15>0),B15/F15,"") | H15: =IFERROR(B15/B14-1,"") -> -0.1758353 | I15: Missing in WITS; not zero | J15: https://wits.worldbank.org/trade/comtrade/en/country/COL/year/2025/tradeflow/Imports/partner/ALL/product/271111 | K15: https://wits.worldbank.org/trade/comtrade/en/country/COL/year/2025/tradeflow/Imports/partner/ALL/product/271121
A18: CIF is not FOB. The annual series alone cannot give an exact contribution to the FOB merchandise-trade balance. Unit values are customs ratios, not LNG spot prices.

Sheet Annual raw
A1: ANNUAL RAW | PUBLISHED WORLD TOTALS
A2: Source values are displayed in US$ thousands on WITS. Converted dollars are formulas. Quantity is the WITS reported quantity field in kg; missing weights stay blank.
A6: Year | B6: HS6 | C6: Product | D6: Source value (US$ thousands) | E6: Reported quantity (kg) | F6: CIF value (US$) | G6: Quantity status | H6: Source URL | I6: Accessed
A7: 2017 | B7: 271111 | C7: LNG | D7: 11925.93 | E7: 38942600 | F7: =D7*Settings!$B$7 -> 11925930 | G7: reported | H7: https://wits.worldbank.org/trade/comtrade/en/country/COL/year/2017/tradeflow/Imports/partner/ALL/product/271111 | I7: 2026-10-27
A8: 2018 | B8: 271111 | C8: LNG | D8: 123747.36 | E8: 239638000 | F8: =D8*Settings!$B$7 -> 123747360 | G8: reported | H8: https://wits.worldbank.org/trade/comtrade/en/country/COL/year/2018/tradeflow/Imports/partner/ALL/product/271111 | I8: 2026-10-27
A9: 2019 | B9: 271111 | C9: LNG | D9: 57044.06 | F9: =D9*Settings!$B$7 -> 57044060 | G9: missing_not_zero | H9: https://wits.worldbank.org/trade/comtrade/en/country/COL/year/2019/tradeflow/Imports/partner/ALL/product/271111 | I9: 2026-10-27
A10: 2020 | B10: 271111 | C10: LNG | D10: 59910.33 | E10: 296302000 | F10: =D10*Settings!$B$7 -> 59910330 | G10: reported | H10: https://wits.worldbank.org/trade/comtrade/en/country/COL/year/2020/tradeflow/Imports/partner/ALL/product/271111 | I10: 2026-10-27
A11: 2021 | B11: 271111 | C11: LNG | D11: 27941.49 | E11: 44406000 | F11: =D11*Settings!$B$7 -> 27941490 | G11: reported | H11: https://wits.worldbank.org/trade/comtrade/en/country/COL/year/2021/tradeflow/Imports/partner/ALL/product/271111 | I11: 2026-10-27
A12: 2021 | B12: 271121 | C12: Natural gas, gaseous | D12: 43.16 | E12: 3843 | F12: =D12*Settings!$B$7 -> 43160 | G12: reported | H12: https://wits.worldbank.org/trade/comtrade/en/country/COL/year/2021/tradeflow/Imports/partner/ALL/product/271121 | I12: 2026-10-27
A13: 2022 | B13: 271111 | C13: LNG | D13: 87550.64 | E13: 60181000 | F13: =D13*Settings!$B$7 -> 87550640 | G13: reported | H13: https://wits.worldbank.org/trade/comtrade/en/country/COL/year/2022/tradeflow/Imports/partner/ALL/product/271111 | I13: 2026-10-27
A14: 2022 | B14: 271121 | C14: Natural gas, gaseous | D14: 84.12 | E14: 4095 | F14: =D14*Settings!$B$7 -> 84120 | G14: reported | H14: https://wits.worldbank.org/trade/comtrade/en/country/COL/year/2022/tradeflow/Imports/partner/ALL/product/271121 | I14: 2026-10-27
A15: 2023 | B15: 271111 | C15: LNG | D15: 441455.97 | F15: =D15*Settings!$B$7 -> 441455970 | G15: missing_not_zero | H15: https://wits.worldbank.org/trade/comtrade/en/country/COL/year/2023/tradeflow/Imports/partner/ALL/product/271111 | I15: 2026-10-27
A16: 2023 | B16: 271121 | C16: Natural gas, gaseous | D16: 4.93 | E16: 5995 | F16: =D16*Settings!$B$7 -> 4930 | G16: reported | H16: https://wits.worldbank.org/trade/comtrade/en/country/COL/year/2023/tradeflow/Imports/partner/ALL/product/271121 | I16: 2026-10-27
A17: 2024 | B17: 271111 | C17: LNG | D17: 945446.54 | E17: 1625300000 | F17: =D17*Settings!$B$7 -> 945446540 | G17: reported | H17: https://wits.worldbank.org/trade/comtrade/en/country/COL/year/2024/tradeflow/Imports/partner/ALL/product/271111 | I17: 2026-10-27
A18: 2024 | B18: 271121 | C18: Natural gas, gaseous | D18: 31.74 | E18: 935 | F18: =D18*Settings!$B$7 -> 31740 | G18: reported | H18: https://wits.worldbank.org/trade/comtrade/en/country/COL/year/2024/tradeflow/Imports/partner/ALL/product/271121 | I18: 2026-10-27
A19: 2025 | B19: 271111 | C19: LNG | D19: 779203.66 | F19: =D19*Settings!$B$7 -> 779203660 | G19: missing_not_zero | H19: https://wits.worldbank.org/trade/comtrade/en/country/COL/year/2025/tradeflow/Imports/partner/ALL/product/271111 | I19: 2026-10-27
A20: 2025 | B20: 271121 | C20: Natural gas, gaseous | D20: 27.57 | F20: =D20*Settings!$B$7 -> 27570 | G20: missing_not_zero | H20: https://wits.worldbank.org/trade/comtrade/en/country/COL/year/2025/tradeflow/Imports/partner/ALL/product/271121 | I20: 2026-10-27

Sheet Partners
A1: PARTNER DETAIL | ANNUAL IMPORTS
A2: Raw partner labels are preserved. The 2025 LNG analysis label for Tanzania is reconciled to Trinidad and Tobago using DANE, and is explicitly flagged. Do not infer liquefaction origin from partner labels.
A6: Year | B6: HS6 | C6: Partner reported | D6: Partner for analysis | E6: Source value (US$ thousands) | F6: CIF value (US$) | G6: Reported quantity (kg) | H6: Quality / reconciliation note | I6: Source URL | J6: Reconciliation URL
A7: 2017 | B7: 271111 | C7: Switzerland | D7: Switzerland | E7: 11925.93 | F7: =E7*Settings!$B$7 -> 11925930 | G7: 38942600 | H7: Reported trade partner. Do not automatically interpret as liquefaction/production origin. | I7: https://wits.worldbank.org/trade/comtrade/en/country/COL/year/2017/tradeflow/Imports/partner/ALL/product/271111
A8: 2018 | B8: 271111 | C8: United States | D8: United States | E8: 39553.93 | F8: =E8*Settings!$B$7 -> 39553930 | G8: 69076600 | I8: https://wits.worldbank.org/trade/comtrade/en/country/COL/year/2018/tradeflow/Imports/partner/ALL/product/271111
A9: 2018 | B9: 271111 | C9: Trinidad and Tobago | D9: Trinidad and Tobago | E9: 36711.02 | F9: =E9*Settings!$B$7 -> 36711020 | G9: 71101100 | I9: https://wits.worldbank.org/trade/comtrade/en/country/COL/year/2018/tradeflow/Imports/partner/ALL/product/271111
A10: 2018 | B10: 271111 | C10: United Kingdom | D10: United Kingdom | E10: 32602.78 | F10: =E10*Settings!$B$7 -> 32602780 | G10: 68334300 | H10: Reported trade partner. Do not automatically interpret as liquefaction/production origin. | I10: https://wits.worldbank.org/trade/comtrade/en/country/COL/year/2018/tradeflow/Imports/partner/ALL/product/271111
A11: 2018 | B11: 271111 | C11: Switzerland | D11: Switzerland | E11: 14878.74 | F11: =E11*Settings!$B$7 -> 14878740 | G11: 31125900 | H11: Reported trade partner. Do not automatically interpret as liquefaction/production origin. | I11: https://wits.worldbank.org/trade/comtrade/en/country/COL/year/2018/tradeflow/Imports/partner/ALL/product/271111
A12: 2018 | B12: 271111 | C12: Peru | D12: Peru | E12: 0.9 | F12: =E12*Settings!$B$7 -> 900 | G12: 14 | I12: https://wits.worldbank.org/trade/comtrade/en/country/COL/year/2018/tradeflow/Imports/partner/ALL/product/271111
A13: 2019 | B13: 271111 | C13: Ireland | D13: Ireland | E13: 27308.73 | F13: =E13*Settings!$B$7 -> 27308730 | G13: 66112400 | H13: Reported trade partner. Do not automatically interpret as liquefaction/production origin. | I13: https://wits.worldbank.org/trade/comtrade/en/country/COL/year/2019/tradeflow/Imports/partner/ALL/product/271111
A14: 2019 | B14: 271111 | C14: United States | D14: United States | E14: 21902.39 | F14: =E14*Settings!$B$7 -> 21902390 | I14: https://wits.worldbank.org/trade/comtrade/en/country/COL/year/2019/tradeflow/Imports/partner/ALL/product/271111
A15: 2019 | B15: 271111 | C15: Trinidad and Tobago | D15: Trinidad and Tobago | E15: 7832.93 | F15: =E15*Settings!$B$7 -> 7832930 | G15: 34111700 | I15: https://wits.worldbank.org/trade/comtrade/en/country/COL/year/2019/tradeflow/Imports/partner/ALL/product/271111
A16: 2020 | B16: 271111 | C16: United Arab Emirates | D16: United Arab Emirates | E16: 21633.89 | F16: =E16*Settings!$B$7 -> 21633890 | G16: 116121000 | H16: Reported trade partner. Do not automatically interpret as liquefaction/production origin. | I16: https://wits.worldbank.org/trade/comtrade/en/country/COL/year/2020/tradeflow/Imports/partner/ALL/product/271111
A17: 2020 | B17: 271111 | C17: United Kingdom | D17: United Kingdom | E17: 20339.8 | F17: =E17*Settings!$B$7 -> 20339800 | G17: 88247200 | H17: Reported trade partner. Do not automatically interpret as liquefaction/production origin. | I17: https://wits.worldbank.org/trade/comtrade/en/country/COL/year/2020/tradeflow/Imports/partner/ALL/product/271111
A18: 2020 | B18: 271111 | C18: Trinidad and Tobago | D18: Trinidad and Tobago | E18: 13410.35 | F18: =E18*Settings!$B$7 -> 13410350 | G18: 70111100 | I18: https://wits.worldbank.org/trade/comtrade/en/country/COL/year/2020/tradeflow/Imports/partner/ALL/product/271111
A19: 2020 | B19: 271111 | C19: United States | D19: United States | E19: 2972.81 | F19: =E19*Settings!$B$7 -> 2972810 | G19: 10708100 | I19: https://wits.worldbank.org/trade/comtrade/en/country/COL/year/2020/tradeflow/Imports/partner/ALL/product/271111
A20: 2020 | B20: 271111 | C20: Switzerland | D20: Switzerland | E20: 1553.47 | F20: =E20*Settings!$B$7 -> 1553470 | G20: 11114600 | H20: Reported trade partner. Do not automatically interpret as liquefaction/production origin. | I20: https://wits.worldbank.org/trade/comtrade/en/country/COL/year/2020/tradeflow/Imports/partner/ALL/product/271111
A21: 2021 | B21: 271111 | C21: United States | D21: United States | E21: 14510.52 | F21: =E21*Settings!$B$7 -> 14510520 | G21: 18165700 | I21: https://wits.worldbank.org/trade/comtrade/en/country/COL/year/2021/tradeflow/Imports/partner/ALL/product/271111
A22: 2021 | B22: 271111 | C22: United Kingdom | D22: United Kingdom | E22: 13422.46 | F22: =E22*Settings!$B$7 -> 13422460 | G22: 26237900 | H22: Reported trade partner. Do not automatically interpret as liquefaction/production origin. | I22: https://wits.worldbank.org/trade/comtrade/en/country/COL/year/2021/tradeflow/Imports/partner/ALL/product/271111
A23: 2021 | B23: 271111 | C23: Canada | D23: Canada | E23: 4.46 | F23: =E23*Settings!$B$7 -> 4460 | G23: 517 | I23: https://wits.worldbank.org/trade/comtrade/en/country/COL/year/2021/tradeflow/Imports/partner/ALL/product/271111
A24: 2021 | B24: 271111 | C24: Bolivia | D24: Bolivia | E24: 4.05 | F24: =E24*Settings!$B$7 -> 4050 | G24: 1815 | I24: https://wits.worldbank.org/trade/comtrade/en/country/COL/year/2021/tradeflow/Imports/partner/ALL/product/271111
A25: 2021 | B25: 271121 | C25: United States | D25: United States | E25: 29.64 | F25: =E25*Settings!$B$7 -> 29640 | G25: 837 | I25: https://wits.worldbank.org/trade/comtrade/en/country/COL/year/2021/tradeflow/Imports/partner/ALL/product/271121
A26: 2021 | B26: 271121 | C26: China | D26: China | E26: 13.51 | F26: =E26*Settings!$B$7 -> 13510 | G26: 3006 | I26: https://wits.worldbank.org/trade/comtrade/en/country/COL/year/2021/tradeflow/Imports/partner/ALL/product/271121
A27: 2022 | B27: 271111 | C27: United States | D27: United States | E27: 87550.64 | F27: =E27*Settings!$B$7 -> 87550640 | G27: 60181000 | I27: https://wits.worldbank.org/trade/comtrade/en/country/COL/year/2022/tradeflow/Imports/partner/ALL/product/271111
A28: 2022 | B28: 271121 | C28: United States | D28: United States | E28: 75.04 | F28: =E28*Settings!$B$7 -> 75040 | G28: 1724 | I28: https://wits.worldbank.org/trade/comtrade/en/country/COL/year/2022/tradeflow/Imports/partner/ALL/product/271121
A29: 2022 | B29: 271121 | C29: China | D29: China | E29: 9.08 | F29: =E29*Settings!$B$7 -> 9080 | G29: 2370 | I29: https://wits.worldbank.org/trade/comtrade/en/country/COL/year/2022/tradeflow/Imports/partner/ALL/product/271121
A30: 2023 | B30: 271111 | C30: United States | D30: United States | E30: 410852.09 | F30: =E30*Settings!$B$7 -> 410852090 | G30: 587226000 | I30: https://wits.worldbank.org/trade/comtrade/en/country/COL/year/2023/tradeflow/Imports/partner/ALL/product/271111
A31: 2023 | B31: 271111 | C31: Trinidad and Tobago | D31: Trinidad and Tobago | E31: 30603.01 | F31: =E31*Settings!$B$7 -> 30603010 | G31: 38373800 | I31: https://wits.worldbank.org/trade/comtrade/en/country/COL/year/2023/tradeflow/Imports/partner/ALL/product/271111
A32: 2023 | B32: 271111 | C32: United Kingdom | D32: United Kingdom | E32: 0.87 | F32: =E32*Settings!$B$7 -> 870 | H32: Reported trade partner. Do not automatically interpret as liquefaction/production origin. | I32: https://wits.worldbank.org/trade/comtrade/en/country/COL/year/2023/tradeflow/Imports/partner/ALL/product/271111
A33: 2023 | B33: 271121 | C33: United States | D33: United States | E33: 4.93 | F33: =E33*Settings!$B$7 -> 4930 | G33: 5995 | I33: https://wits.worldbank.org/trade/comtrade/en/country/COL/year/2023/tradeflow/Imports/partner/ALL/product/271121
A34: 2024 | B34: 271111 | C34: United States | D34: United States | E34: 771978.25 | F34: =E34*Settings!$B$7 -> 771978250 | G34: 1383020000 | I34: https://wits.worldbank.org/trade/comtrade/en/country/COL/year/2024/tradeflow/Imports/partner/ALL/product/271111
A35: 2024 | B35: 271111 | C35: Trinidad and Tobago | D35: Trinidad and Tobago | E35: 134542.94 | F35: =E35*Settings!$B$7 -> 134542940 | G35: 192276000 | I35: https://wits.worldbank.org/trade/comtrade/en/country/COL/year/2024/tradeflow/Imports/partner/ALL/product/271111
A36: 2024 | B36: 271111 | C36: United Kingdom | D36: United Kingdom | E36: 38925.35 | F36: =E36*Settings!$B$7 -> 38925350 | G36: 50000800 | H36: Reported trade partner. Do not automatically interpret as liquefaction/production origin. | I36: https://wits.worldbank.org/trade/comtrade/en/country/COL/year/2024/tradeflow/Imports/partner/ALL/product/271111
A37: 2024 | B37: 271121 | C37: United States | D37: United States | E37: 25.29 | F37: =E37*Settings!$B$7 -> 25290 | G37: 392 | I37: https://wits.worldbank.org/trade/comtrade/en/country/COL/year/2024/tradeflow/Imports/partner/ALL/product/271121
A38: 2024 | B38: 271121 | C38: Unspecified | D38: Unspecified | E38: 6.45 | F38: =E38*Settings!$B$7 -> 6450 | G38: 543 | I38: https://wits.worldbank.org/trade/comtrade/en/country/COL/year/2024/tradeflow/Imports/partner/ALL/product/271121
A39: 2025 | B39: 271111 | C39: Tanzania | D39: Trinidad and Tobago | E39: 390808.22 | F39: =E39*Settings!$B$7 -> 390808220 | G39: 597442000 | H39: Raw WITS label Tanzania retained. Analysis label reconciled to DANE Dec-2025 p11 (US$390.8m). This is an analyst reconciliation, not an upstream correction. | I39: https://wits.worldbank.org/trade/comtrade/en/country/COL/year/2025/tradeflow/Imports/partner/ALL/product/271111 | J39: https://www.dane.gov.co/files/operaciones/IMP/bol-IMP-dic2025.pdf
A40: 2025 | B40: 271111 | C40: United States | D40: United States | E40: 388390.81 | F40: =E40*Settings!$B$7 -> 388390810 | I40: https://wits.worldbank.org/trade/comtrade/en/country/COL/year/2025/tradeflow/Imports/partner/ALL/product/271111
A41: 2025 | B41: 271111 | C41: United Kingdom | D41: United Kingdom | E41: 4.63 | F41: =E41*Settings!$B$7 -> 4630 | G41: 6939 | H41: Reported trade partner. Do not automatically interpret as liquefaction/production origin. | I41: https://wits.worldbank.org/trade/comtrade/en/country/COL/year/2025/tradeflow/Imports/partner/ALL/product/271111
A42: 2025 | B42: 271121 | C42: United States | D42: United States | E42: 25.28 | F42: =E42*Settings!$B$7 -> 25280 | I42: https://wits.worldbank.org/trade/comtrade/en/country/COL/year/2025/tradeflow/Imports/partner/ALL/product/271121
A43: 2025 | B43: 271121 | C43: Australia | D43: Australia | E43: 2.29 | F43: =E43*Settings!$B$7 -> 2290 | I43: https://wits.worldbank.org/trade/comtrade/en/country/COL/year/2025/tradeflow/Imports/partner/ALL/product/271121

Sheet BMC scenario
A1: BMC | VISIBLE FORWARD SCENARIO
A2: Exact table cells from the user screenshot: UPME + OEF XM. This is total supply versus demand, NOT projected LNG imports. Yellow domestic-supply inputs are intentionally blank; price is an illustrative assumption.
A6: Month | B6: Supply (MBtu/day) | C6: Demand projection (MBtu/day) | D6: Published margin (MBtu/day) | E6: Calculated margin (MBtu/day) | F6: Margin check | G6: Usable domestic supply (input, MBtu/day) | H6: Residual import need (MBtu/day) | I6: Border LNG price (US$/MMBtu) | J6: Days in month | K6: Indicative monthly LNG bill (US$ million) | L6: Scenario | M6: Source / provenance
A7: 46296 | B7: 1144175 | C7: 1205885 | D7: -61710 | E7: =B7-C7 -> -61710 | F7: =IF(E7=D7,"PASS","REVIEW") -> PASS | H7: =IF(ISNUMBER(G7),MAX(0,C7-G7),"") | I7: =Settings!$B$10 -> 12 | J7: =DAY(EOMONTH(A7,0)) -> 31 | K7: =IF(AND(ISNUMBER(G7),G7>=0),H7*I7*J7/Settings!$B$8,"") | L7: UPME + OEF XM | M7: User screenshot: exact visible table; https://www.bmcbec.com.co/
A8: 46327 | B8: 1257285 | C8: 1184705 | D8: 72580 | E8: =B8-C8 -> 72580 | F8: =IF(E8=D8,"PASS","REVIEW") -> PASS | H8: =IF(ISNUMBER(G8),MAX(0,C8-G8),"") | I8: =Settings!$B$10 -> 12 | J8: =DAY(EOMONTH(A8,0)) -> 30 | K8: =IF(AND(ISNUMBER(G8),G8>=0),H8*I8*J8/Settings!$B$8,"") | L8: UPME + OEF XM | M8: User screenshot: exact visible table; https://www.bmcbec.com.co/
A9: 46357 | B9: 1245033 | C9: 1293349 | D9: -48316 | E9: =B9-C9 -> -48316 | F9: =IF(E9=D9,"PASS","REVIEW") -> PASS | H9: =IF(ISNUMBER(G9),MAX(0,C9-G9),"") | I9: =Settings!$B$10 -> 12 | J9: =DAY(EOMONTH(A9,0)) -> 31 | K9: =IF(AND(ISNUMBER(G9),G9>=0),H9*I9*J9/Settings!$B$8,"") | L9: UPME + OEF XM | M9: User screenshot: exact visible table; https://www.bmcbec.com.co/
A10: 46388 | B10: 1234062 | C10: 1282217 | D10: -48155 | E10: =B10-C10 -> -48155 | F10: =IF(E10=D10,"PASS","REVIEW") -> PASS | H10: =IF(ISNUMBER(G10),MAX(0,C10-G10),"") | I10: =Settings!$B$10 -> 12 | J10: =DAY(EOMONTH(A10,0)) -> 31 | K10: =IF(AND(ISNUMBER(G10),G10>=0),H10*I10*J10/Settings!$B$8,"") | L10: UPME + OEF XM | M10: User screenshot: exact visible table; https://www.bmcbec.com.co/
A11: 46419 | B11: 1261486 | C11: 1301626 | D11: -40140 | E11: =B11-C11 -> -40140 | F11: =IF(E11=D11,"PASS","REVIEW") -> PASS | H11: =IF(ISNUMBER(G11),MAX(0,C11-G11),"") | I11: =Settings!$B$10 -> 12 | J11: =DAY(EOMONTH(A11,0)) -> 28 | K11: =IF(AND(ISNUMBER(G11),G11>=0),H11*I11*J11/Settings!$B$8,"") | L11: UPME + OEF XM | M11: User screenshot: exact visible table; https://www.bmcbec.com.co/
A12: 46447 | B12: 1268968 | C12: 1317922 | D12: -48954 | E12: =B12-C12 -> -48954 | F12: =IF(E12=D12,"PASS","REVIEW") -> PASS | H12: =IF(ISNUMBER(G12),MAX(0,C12-G12),"") | I12: =Settings!$B$10 -> 12 | J12: =DAY(EOMONTH(A12,0)) -> 31 | K12: =IF(AND(ISNUMBER(G12),G12>=0),H12*I12*J12/Settings!$B$8,"") | L12: UPME + OEF XM | M12: User screenshot: exact visible table; https://www.bmcbec.com.co/
A13: 46478 | B13: 1267109 | C13: 1104530 | D13: 162579 | E13: =B13-C13 -> 162579 | F13: =IF(E13=D13,"PASS","REVIEW") -> PASS | H13: =IF(ISNUMBER(G13),MAX(0,C13-G13),"") | I13: =Settings!$B$10 -> 12 | J13: =DAY(EOMONTH(A13,0)) -> 30 | K13: =IF(AND(ISNUMBER(G13),G13>=0),H13*I13*J13/Settings!$B$8,"") | L13: UPME + OEF XM | M13: User screenshot: exact visible table; https://www.bmcbec.com.co/
A14: 46508 | B14: 1263599 | C14: 1089386 | D14: 174213 | E14: =B14-C14 -> 174213 | F14: =IF(E14=D14,"PASS","REVIEW") -> PASS | H14: =IF(ISNUMBER(G14),MAX(0,C14-G14),"") | I14: =Settings!$B$10 -> 12 | J14: =DAY(EOMONTH(A14,0)) -> 31 | K14: =IF(AND(ISNUMBER(G14),G14>=0),H14*I14*J14/Settings!$B$8,"") | L14: UPME + OEF XM | M14: User screenshot: exact visible table; https://www.bmcbec.com.co/
A15: 46539 | B15: 1267572 | C15: 1186340 | D15: 81232 | E15: =B15-C15 -> 81232 | F15: =IF(E15=D15,"PASS","REVIEW") -> PASS | H15: =IF(ISNUMBER(G15),MAX(0,C15-G15),"") | I15: =Settings!$B$10 -> 12 | J15: =DAY(EOMONTH(A15,0)) -> 30 | K15: =IF(AND(ISNUMBER(G15),G15>=0),H15*I15*J15/Settings!$B$8,"") | L15: UPME + OEF XM | M15: User screenshot: exact visible table; https://www.bmcbec.com.co/
A16: 46569 | B16: 1277866 | C16: 1133719 | D16: 144147 | E16: =B16-C16 -> 144147 | F16: =IF(E16=D16,"PASS","REVIEW") -> PASS | H16: =IF(ISNUMBER(G16),MAX(0,C16-G16),"") | I16: =Settings!$B$10 -> 12 | J16: =DAY(EOMONTH(A16,0)) -> 31 | K16: =IF(AND(ISNUMBER(G16),G16>=0),H16*I16*J16/Settings!$B$8,"") | L16: UPME + OEF XM | M16: User screenshot: exact visible table; https://www.bmcbec.com.co/
A17: 46600 | B17: 1281951 | C17: 1127004 | D17: 154947 | E17: =B17-C17 -> 154947 | F17: =IF(E17=D17,"PASS","REVIEW") -> PASS | H17: =IF(ISNUMBER(G17),MAX(0,C17-G17),"") | I17: =Settings!$B$10 -> 12 | J17: =DAY(EOMONTH(A17,0)) -> 31 | K17: =IF(AND(ISNUMBER(G17),G17>=0),H17*I17*J17/Settings!$B$8,"") | L17: UPME + OEF XM | M17: User screenshot: exact visible table; https://www.bmcbec.com.co/
A18: 46631 | B18: 1282211 | C18: 989533 | D18: 292678 | E18: =B18-C18 -> 292678 | F18: =IF(E18=D18,"PASS","REVIEW") -> PASS | H18: =IF(ISNUMBER(G18),MAX(0,C18-G18),"") | I18: =Settings!$B$10 -> 12 | J18: =DAY(EOMONTH(A18,0)) -> 30 | K18: =IF(AND(ISNUMBER(G18),G18>=0),H18*I18*J18/Settings!$B$8,"") | L18: UPME + OEF XM | M18: User screenshot: exact visible table; https://www.bmcbec.com.co/
... A20: 46692 | B20: 1312109 | C20: 986976 | D20: 325133 | E20: =B20-C20 -> 325133 | F20: =IF(E20=D20,"PASS","REVIEW") -> PASS | H20: =IF(ISNUMBER(G20),MAX(0,C20-G20),"") | I20: =Settings!$B$10 -> 12 | J20: =DAY(EOMONTH(A20,0)) -> 30 | K20: =IF(AND(ISNUMBER(G20),G20>=0),H20*I20*J20/Settings!$B$8,"") | L20: UPME + OEF XM | M20: User screenshot: exact visible table; https://www.bmcbec.com.co/
A23: Residual import need = max(0, demand - usable domestic supply). It is uncapped demand for imported gas, not contracted cargoes. Total supply in column B already includes import-related components; never enter B into G.
A25: Only the 14 displayed rows were transcribed. No 2028 values or terminal-specific volumes were guessed from the stacked bars. Scenario prices and actual customs costs remain separate.

Sheet Selected monthly
A1: SELECTED MONTHLY | NOT NATIONAL TOTALS
A2: Only two LNG observations for Trinidad and Tobago from DANE August 2026 bulletin, p. 9. These are provisional, rounded and partner-specific; they are NOT a complete monthly series.
A6: Month | B6: Origin partner | C6: Product label | D6: CIF value (US$ million) | E6: CIF value (US$) | F6: Coverage | G6: Source URL | H6: Source page
A7: 45870 | B7: Trinidad and Tobago | C7: Gas natural licuado | D7: 21.4 | E7: =D7*Settings!$B$8 -> 21400000 | F7: One partner only - not national total | G7: https://www.dane.gov.co/files/operaciones/IMP/bol-IMP-ago2026.pdf | H7: 9
A8: 46235 | B8: Trinidad and Tobago | C8: Gas natural licuado | D8: 195.8 | E8: =D8*Settings!$B$8 -> 195800000 | F8: One partner only - not national total | G8: https://www.dane.gov.co/files/operaciones/IMP/bol-IMP-ago2026.pdf | H8: 9
A11: Do not combine these two partner observations with national totals as though they were the same series. This sheet does not establish the 2026 national LNG import bill.

Sheet Monthly imports
A1: MONTHLY CUSTOMS MICRODATA | NOT LOADED
A2: Bulk national customs schema remains empty. The new Monthly long / DIAN raw tabs contain 20 screenshot observations, quarantined from this table because HS and flow filters are not visible.
A6: Month | B6: HS6 | C6: HS10 | D6: Origin code | E6: Country-code scheme | F6: Origin name | G6: FOB (US$) | H6: CIF (US$) | I6: Net weight (kg) | J6: Source file | K6: Source URL
A9: ZERO NATIONAL MONTHLY ROWS LOADED. Missing observations have not been fabricated or spread evenly across months.

Sheet Checks
A1: VALIDATION | RECONCILIATION
A2: Dollar checks compare WITS world totals against their partner rows. Small differences arise because WITS values are rounded to US$10. Missing quantities are not imputed.
A6: Year | B6: HS6 | C6: World CIF (US$) | D6: Sum of partners (US$) | E6: Residual (US$) | F6: Tolerance (US$) | G6: Check | H6: Quantity missing? | I6: Source URL
A7: 2017 | B7: 271111 | C7: ='Annual raw'!F7 -> 11925930 | D7: =SUMIFS(Partners!$F$7:$F$43,Partners!$A$7:$A$43,A7,Partners!$B$7:$B$43,B7) -> 11925930 | E7: =C7-D7 -> 0 | F7: =Settings!$B$11 -> 50 | G7: =IF(ABS(E7)<=F7,"PASS","REVIEW") -> PASS | H7: NO | I7: https://wits.worldbank.org/trade/comtrade/en/country/COL/year/2017/tradeflow/Imports/partner/ALL/product/271111
A8: 2018 | B8: 271111 | C8: ='Annual raw'!F8 -> 123747360 | D8: =SUMIFS(Partners!$F$7:$F$43,Partners!$A$7:$A$43,A8,Partners!$B$7:$B$43,B8) -> 123747370 | E8: =C8-D8 -> -10 | F8: =Settings!$B$11 -> 50 | G8: =IF(ABS(E8)<=F8,"PASS","REVIEW") -> PASS | H8: NO | I8: https://wits.worldbank.org/trade/comtrade/en/country/COL/year/2018/tradeflow/Imports/partner/ALL/product/271111
A9: 2019 | B9: 271111 | C9: ='Annual raw'!F9 -> 57044060 | D9: =SUMIFS(Partners!$F$7:$F$43,Partners!$A$7:$A$43,A9,Partners!$B$7:$B$43,B9) -> 57044050 | E9: =C9-D9 -> 10 | F9: =Settings!$B$11 -> 50 | G9: =IF(ABS(E9)<=F9,"PASS","REVIEW") -> PASS | H9: YES | I9: https://wits.worldbank.org/trade/comtrade/en/country/COL/year/2019/tradeflow/Imports/partner/ALL/product/271111
A10: 2020 | B10: 271111 | C10: ='Annual raw'!F10 -> 59910330 | D10: =SUMIFS(Partners!$F$7:$F$43,Partners!$A$7:$A$43,A10,Partners!$B$7:$B$43,B10) -> 59910320 | E10: =C10-D10 -> 10 | F10: =Settings!$B$11 -> 50 | G10: =IF(ABS(E10)<=F10,"PASS","REVIEW") -> PASS | H10: NO | I10: https://wits.worldbank.org/trade/comtrade/en/country/COL/year/2020/tradeflow/Imports/partner/ALL/product/271111
A11: 2021 | B11: 271111 | C11: ='Annual raw'!F11 -> 27941490 | D11: =SUMIFS(Partners!$F$7:$F$43,Partners!$A$7:$A$43,A11,Partners!$B$7:$B$43,B11) -> 27941490 | E11: =C11-D11 -> 0 | F11: =Settings!$B$11 -> 50 | G11: =IF(ABS(E11)<=F11,"PASS","REVIEW") -> PASS | H11: NO | I11: https://wits.worldbank.org/trade/comtrade/en/country/COL/year/2021/tradeflow/Imports/partner/ALL/product/271111
A12: 2021 | B12: 271121 | C12: ='Annual raw'!F12 -> 43160 | D12: =SUMIFS(Partners!$F$7:$F$43,Partners!$A$7:$A$43,A12,Partners!$B$7:$B$43,B12) -> 43150 | E12: =C12-D12 -> 10 | F12: =Settings!$B$11 -> 50 | G12: =IF(ABS(E12)<=F12,"PASS","REVIEW") -> PASS | H12: NO | I12: https://wits.worldbank.org/trade/comtrade/en/country/COL/year/2021/tradeflow/Imports/partner/ALL/product/271121
A13: 2022 | B13: 271111 | C13: ='Annual raw'!F13 -> 87550640 | D13: =SUMIFS(Partners!$F$7:$F$43,Partners!$A$7:$A$43,A13,Partners!$B$7:$B$43,B13) -> 87550640 | E13: =C13-D13 -> 0 | F13: =Settings!$B$11 -> 50 | G13: =IF(ABS(E13)<=F13,"PASS","REVIEW") -> PASS | H13: NO | I13: https://wits.worldbank.org/trade/comtrade/en/country/COL/year/2022/tradeflow/Imports/partner/ALL/product/271111
A14: 2022 | B14: 271121 | C14: ='Annual raw'!F14 -> 84120 | D14: =SUMIFS(Partners!$F$7:$F$43,Partners!$A$7:$A$43,A14,Partners!$B$7:$B$43,B14) -> 84120 | E14: =C14-D14 -> 0 | F14: =Settings!$B$11 -> 50 | G14: =IF(ABS(E14)<=F14,"PASS","REVIEW") -> PASS | H14: NO | I14: https://wits.worldbank.org/trade/comtrade/en/country/COL/year/2022/tradeflow/Imports/partner/ALL/product/271121
A15: 2023 | B15: 271111 | C15: ='Annual raw'!F15 -> 441455970 | D15: =SUMIFS(Partners!$F$7:$F$43,Partners!$A$7:$A$43,A15,Partners!$B$7:$B$43,B15) -> 441455970 | E15: =C15-D15 -> 0 | F15: =Settings!$B$11 -> 50 | G15: =IF(ABS(E15)<=F15,"PASS","REVIEW") -> PASS | H15: YES | I15: https://wits.worldbank.org/trade/comtrade/en/country/COL/year/2023/tradeflow/Imports/partner/ALL/product/271111
A16: 2023 | B16: 271121 | C16: ='Annual raw'!F16 -> 4930 | D16: =SUMIFS(Partners!$F$7:$F$43,Partners!$A$7:$A$43,A16,Partners!$B$7:$B$43,B16) -> 4930 | E16: =C16-D16 -> 0 | F16: =Settings!$B$11 -> 50 | G16: =IF(ABS(E16)<=F16,"PASS","REVIEW") -> PASS | H16: NO | I16: https://wits.worldbank.org/trade/comtrade/en/country/COL/year/2023/tradeflow/Imports/partner/ALL/product/271121
A17: 2024 | B17: 271111 | C17: ='Annual raw'!F17 -> 945446540 | D17: =SUMIFS(Partners!$F$7:$F$43,Partners!$A$7:$A$43,A17,Partners!$B$7:$B$43,B17) -> 945446540 | E17: =C17-D17 -> 0 | F17: =Settings!$B$11 -> 50 | G17: =IF(ABS(E17)<=F17,"PASS","REVIEW") -> PASS | H17: NO | I17: https://wits.worldbank.org/trade/comtrade/en/country/COL/year/2024/tradeflow/Imports/partner/ALL/product/271111
A18: 2024 | B18: 271121 | C18: ='Annual raw'!F18 -> 31740 | D18: =SUMIFS(Partners!$F$7:$F$43,Partners!$A$7:$A$43,A18,Partners!$B$7:$B$43,B18) -> 31740 | E18: =C18-D18 -> 0 | F18: =Settings!$B$11 -> 50 | G18: =IF(ABS(E18)<=F18,"PASS","REVIEW") -> PASS | H18: NO | I18: https://wits.worldbank.org/trade/comtrade/en/country/COL/year/2024/tradeflow/Imports/partner/ALL/product/271121
... A20: 2025 | B20: 271121 | C20: ='Annual raw'!F20 -> 27570 | D20: =SUMIFS(Partners!$F$7:$F$43,Partners!$A$7:$A$43,A20,Partners!$B$7:$B$43,B20) -> 27570 | E20: =C20-D20 -> 0 | F20: =Settings!$B$11 -> 50 | G20: =IF(ABS(E20)<=F20,"PASS","REVIEW") -> PASS | H20: YES | I20: https://wits.worldbank.org/trade/comtrade/en/country/COL/year/2025/tradeflow/Imports/partner/ALL/product/271121
A23: Additional checks: 14/14 BMC margins reconcile exactly. No national monthly customs observations were loaded. World LNG quantity is missing for 2019, 2023 and 2025.

Sheet Sources
A1: SOURCE REGISTER | AUDIT TRAIL
A2: URLs and retrieval status are retained. Public annual tables were read; this is not a transaction-level DANE archive extraction.
A6: Source ID | B6: Publisher | C6: Document / table | D6: Source URL | E6: Accessed | F6: Scope | G6: Retrieval status
A7: WITS_271111_2017 | B7: World Bank WITS / UN Comtrade | C7: Colombia imports: HS 271111, 2017 | D7: https://wits.worldbank.org/trade/comtrade/en/country/COL/year/2017/tradeflow/Imports/partner/ALL/product/271111 | E7: 2026-10-27 | F7: Annual public summary; monetary values displayed to US$10 precision | G7: Table retrieved; not customs microdata
A8: WITS_271111_2018 | B8: World Bank WITS / UN Comtrade | C8: Colombia imports: HS 271111, 2018 | D8: https://wits.worldbank.org/trade/comtrade/en/country/COL/year/2018/tradeflow/Imports/partner/ALL/product/271111 | E8: 2026-10-27 | F8: Annual public summary; monetary values displayed to US$10 precision | G8: Table retrieved; not customs microdata
A9: WITS_271111_2019 | B9: World Bank WITS / UN Comtrade | C9: Colombia imports: HS 271111, 2019 | D9: https://wits.worldbank.org/trade/comtrade/en/country/COL/year/2019/tradeflow/Imports/partner/ALL/product/271111 | E9: 2026-10-27 | F9: Annual public summary; monetary values displayed to US$10 precision | G9: Table retrieved; not customs microdata
A10: WITS_271111_2020 | B10: World Bank WITS / UN Comtrade | C10: Colombia imports: HS 271111, 2020 | D10: https://wits.worldbank.org/trade/comtrade/en/country/COL/year/2020/tradeflow/Imports/partner/ALL/product/271111 | E10: 2026-10-27 | F10: Annual public summary; monetary values displayed to US$10 precision | G10: Table retrieved; not customs microdata
A11: WITS_271111_2021 | B11: World Bank WITS / UN Comtrade | C11: Colombia imports: HS 271111, 2021 | D11: https://wits.worldbank.org/trade/comtrade/en/country/COL/year/2021/tradeflow/Imports/partner/ALL/product/271111 | E11: 2026-10-27 | F11: Annual public summary; monetary values displayed to US$10 precision | G11: Table retrieved; not customs microdata
A12: WITS_271121_2021 | B12: World Bank WITS / UN Comtrade | C12: Colombia imports: HS 271121, 2021 | D12: https://wits.worldbank.org/trade/comtrade/en/country/COL/year/2021/tradeflow/Imports/partner/ALL/product/271121 | E12: 2026-10-27 | F12: Annual public summary; monetary values displayed to US$10 precision | G12: Table retrieved; not customs microdata
A13: WITS_271111_2022 | B13: World Bank WITS / UN Comtrade | C13: Colombia imports: HS 271111, 2022 | D13: https://wits.worldbank.org/trade/comtrade/en/country/COL/year/2022/tradeflow/Imports/partner/ALL/product/271111 | E13: 2026-10-27 | F13: Annual public summary; monetary values displayed to US$10 precision | G13: Table retrieved; not customs microdata
A14: WITS_271121_2022 | B14: World Bank WITS / UN Comtrade | C14: Colombia imports: HS 271121, 2022 | D14: https://wits.worldbank.org/trade/comtrade/en/country/COL/year/2022/tradeflow/Imports/partner/ALL/product/271121 | E14: 2026-10-27 | F14: Annual public summary; monetary values displayed to US$10 precision | G14: Table retrieved; not customs microdata
A15: WITS_271111_2023 | B15: World Bank WITS / UN Comtrade | C15: Colombia imports: HS 271111, 2023 | D15: https://wits.worldbank.org/trade/comtrade/en/country/COL/year/2023/tradeflow/Imports/partner/ALL/product/271111 | E15: 2026-10-27 | F15: Annual public summary; monetary values displayed to US$10 precision | G15: Table retrieved; not customs microdata
A16: WITS_271121_2023 | B16: World Bank WITS / UN Comtrade | C16: Colombia imports: HS 271121, 2023 | D16: https://wits.worldbank.org/trade/comtrade/en/country/COL/year/2023/tradeflow/Imports/partner/ALL/product/271121 | E16: 2026-10-27 | F16: Annual public summary; monetary values displayed to US$10 precision | G16: Table retrieved; not customs microdata
A17: WITS_271111_2024 | B17: World Bank WITS / UN Comtrade | C17: Colombia imports: HS 271111, 2024 | D17: https://wits.worldbank.org/trade/comtrade/en/country/COL/year/2024/tradeflow/Imports/partner/ALL/product/271111 | E17: 2026-10-27 | F17: Annual public summary; monetary values displayed to US$10 precision | G17: Table retrieved; not customs microdata
... A31: DANE_AUG2026_BALANCE | B31: DANE | C31: Imports bulletin August 2026, p.13 | D31: https://www.dane.gov.co/files/operaciones/IMP/bol-IMP-ago2026.pdf | E31: 2026-10-27 | F31: Jan-Aug national FOB trade deficit, 2025 and 2026 | G31: Text and chart page verified

Sheet Dictionary
A1: DATA DICTIONARY | USE AND LIMITS
A2: Trade values, physical supply and forward scenarios have different units and scopes. Keep those distinctions when building graphs or estimating the external-account impact.
A6: Dataset / field | B6: Definition | C6: Unit / coding | D6: Treatment / limitation
A7: Annual world / partner | B7: WITS public annual summaries; world records and partner records are separate. | C7: Calendar year; HS6 | D7: Do not add world totals to countries. This is not declaration-level microdata.
A8: HS 271111 / 2711110000 | B8: Natural gas, liquefied (LNG). | C8: HS6 / Colombian HS10 | D8: Used for the LNG series. LPG is excluded.
A9: HS 271121 / 2711210000 | B9: Natural gas in gaseous state. | C9: HS6 / Colombian HS10 | D9: Separate from LNG. 2017-2020 were not retrieved in this extraction.
A10: CIF value | B10: Customs value including cost, insurance and freight. | C10: US$ | D10: Annual WITS values are CIF import values; do not use as exact FOB trade-balance contributions.
A11: FOB value | B11: Value excluding international freight and insurance. | C11: US$; DANE field VAFODO | D11: Required for an exact comparison with the FOB merchandise-trade balance. Not available in the populated annual tables.
A12: Reported quantity | B12: WITS quantity field, where provided in kg. | C12: kg; converted to metric tonnes | D12: Missing quantities remain null. Do not sum incomplete partners into a world quantity.
A13: CIF unit value | B13: CIF dollar value divided by reported quantity in tonnes. | C13: US$/tonne | D13: Not a spot LNG price or a domestic tariff. Very small gaseous-gas trade may be non-bulk shipments.
A14: Partner reported | B14: Country label exactly as displayed by WITS. | C14: Text | D14: May not identify the liquefaction country. Labels such as Switzerland and Ireland should not be relabelled without evidence.
A15: Partner for analysis | B15: Reported label except the flagged 2025 LNG reconciliation. | C15: Text | D15: Tanzania -> Trinidad and Tobago is supported by DANE December 2025 p11. Raw label remains available.
A16: FECH | B16: DANE date field; dictionary example 2501. | C16: YYMM, e.g. 2501 = January 2025 | D16: Loader also supports YYYYMM and common explicit date formats; ambiguous dates fail rather than silently convert.
A17: NABAN | B17: Colombian customs commodity code. | C17: 10-digit text | D17: Keep as text; filter exactly 2711110000 / 2711210000.
... A32: Macro comparison | B32: Selected-series FOB increase / overall FOB deficit widening. | C32: January-August only | D32: Conditional scale measure; not a verified causal contribution or COP forecast.

Sheet Settings
A1: SETTINGS | CONVERSIONS AND INPUTS
A2: Blue numeric cells are editable assumptions. Unit factors are constants; the price is an illustration, not a market forecast.
A6: Setting | B6: Value | C6: Meaning / source
A7: US$ thousands to US$ | B7: 1000 | C7: Exact unit conversion.
A8: US$ to US$ million | B8: 1000000 | C8: Exact unit conversion.
A9: kg per metric tonne | B9: 1000 | C9: Exact unit conversion.
A10: Illustrative LNG border price | B10: 12 | C10: US$/MMBtu; analyst input only, not observed or forecast.
A11: Published-value rounding tolerance | B11: 50 | C11: US$; allows small rounded partner/world differences.
